test07_max10/serial_s.v
/*
 Produced by NSL Core(version=20151214), IP ARCH, Inc. Sat May 14 10:23:53 2016
 Licensed to :EVALUATION USER
*/
/*
 DO NOT USE ANY PART OF THIS FILE FOR COMMERCIAL PRODUCTS. 
*/

module counter ( p_reset , m_clock , f , countup , reset );
  input p_reset, m_clock;
  wire p_reset, m_clock;
  output [12:0] f;
  wire [12:0] f;
  input countup;
  wire countup;
  input reset;
  wire reset;
  reg [12:0] cnt;
  wire _net_0;
  wire _net_1;

   assign  _net_0 = 
// synthesis translate_off
// synopsys translate_off
(countup)? 
// synthesis translate_on
// synopsys translate_on
((countup)?(cnt != 13'b1010001010000):1'b0)
// synthesis translate_off
// synopsys translate_off
:1'bx
// synthesis translate_on
// synopsys translate_on
;
   assign  _net_1 = 
// synthesis translate_off
// synopsys translate_off
(countup)? 
// synthesis translate_on
// synopsys translate_on
((countup)?(cnt==13'b1010001010000):1'b0)
// synthesis translate_off
// synopsys translate_off
:1'bx
// synthesis translate_on
// synopsys translate_on
;
   assign  f = cnt;
always @(posedge m_clock or posedge p_reset)
  begin
if (p_reset)
     cnt <= 13'b0000000000000;
else 
// synthesis translate_off
// synopsys translate_off
if ((((countup&_net_1)&(countup&_net_0))|(((countup&_net_1)|(countup&_net_0))&reset)))   cnt <= 13'bx; 
  else 
// synthesis translate_on
// synopsys translate_on
if ((countup&_net_1))
      cnt <= 13'b0000000000000;
else if ((countup&_net_0))
      cnt <= (cnt+13'b0000000000001);
else if (reset)
      cnt <= 13'b0000000000000;
end

// synthesis translate_off
// synopsys translate_off
always @(posedge m_clock)
  begin
if (((((countup&_net_1)|(countup&_net_0))|reset)==1'b1) ||
 ((((countup&_net_1)|(countup&_net_0))|reset)==1'b0) ) begin
 if ((((countup&_net_1)&(countup&_net_0))|(((countup&_net_1)|(countup&_net_0))&reset)))
 begin $display("Warning: assign collision(counter:cnt) at %d",$time);

  end
 end
 else 
 $display("Warning: register set hazard(counter:cnt) at %d",$time);

  end

// synthesis translate_on
// synopsys translate_on
endmodule
/*
 Produced by NSL Core(version=20151214), IP ARCH, Inc. Sat May 14 10:23:53 2016
 Licensed to :EVALUATION USER
*/
/*
 Produced by NSL Core(version=20151214), IP ARCH, Inc. Sat May 14 10:23:53 2016
 Licensed to :EVALUATION USER
*/
/*
 DO NOT USE ANY PART OF THIS FILE FOR COMMERCIAL PRODUCTS. 
*/

module serial_s ( p_reset , m_clock , start_send , TDX );
  input p_reset, m_clock;
  wire p_reset, m_clock;
  input start_send;
  wire start_send;
  output TDX;
  wire TDX;
  reg TDX_r;
  reg sending;
  reg [8:0] data;
  reg [3:0] loop;
  wire send;
  wire [3:0] _net_6;
  wire [12:0] _counter_i_f;
  wire _counter_i_countup;
  wire _counter_i_reset;
  wire _counter_i_p_reset;
  wire _counter_i_m_clock;
  wire _net_9;
  wire _net_10;
  reg _reg_11;
  reg _reg_12;
  reg _reg_13;
  reg _reg_14;
  reg _reg_15;
  reg _reg_16;
  reg _reg_17;
  reg _reg_18;
  reg _reg_19;
  reg _reg_20;
  wire _net_21;
  wire _reg_13_goto;
  wire _reg_12_goin;
  wire _net_22;
  wire _reg_13_goin;
  wire _net_23;
  wire _reg_15_goto;
  wire _reg_17_goin;
  wire _net_24;
  wire _reg_16_goto;
  wire _reg_15_goin;
  wire _net_25;
  wire _reg_16_goin;
  wire _net_26;
  wire _reg_17_goto;
  wire _reg_14_goin;
counter counter_i (.m_clock(m_clock), .p_reset(p_reset), .reset(_counter_i_reset), .countup(_counter_i_countup), .f(_counter_i_f));


// synthesis translate_off
// synopsys translate_off
always @(posedge send)
  begin
#1 if (send===1'bx)
 begin
$display("Warning: control hazard(serial_s:send) at %d",$time);
 end
#1 if ((((_net_9&_net_10))===1'bx) || (1'b1)===1'bx) $display("hazard ((_net_9&_net_10) || 1'b1) line 45 at %d\n",$time);
 end

// synthesis translate_on
// synopsys translate_on
   assign  send = (_net_9&_net_10);
   assign  _net_6 = 
// synthesis translate_off
// synopsys translate_off
(_reg_15)? 
// synthesis translate_on
// synopsys translate_on
((_reg_15)?(loop+4'b0001):4'b0)
// synthesis translate_off
// synopsys translate_off
:4'bx
// synthesis translate_on
// synopsys translate_on
;

// synthesis translate_off
// synopsys translate_off
always @(posedge _counter_i_countup)
  begin
#1 if (_counter_i_countup===1'bx)
 begin
$display("Warning: control hazard(serial_s:_counter_i_countup) at %d",$time);
 end
#1 if ((((_reg_16&(~_net_24)))===1'bx) || (1'b1)===1'bx) $display("hazard ((_reg_16&(~_net_24)) || 1'b1) line 56 at %d\n",$time);
#1 if ((((_reg_13&(~_net_21)))===1'bx) || (1'b1)===1'bx) $display("hazard ((_reg_13&(~_net_21)) || 1'b1) line 62 at %d\n",$time);
 end

// synthesis translate_on
// synopsys translate_on
   assign  _counter_i_countup = (_reg_16&(~_net_24))|
    (_reg_13&(~_net_21));

// synthesis translate_off
// synopsys translate_off
always @(posedge _counter_i_reset)
  begin
#1 if (_counter_i_reset===1'bx)
 begin
$display("Warning: control hazard(serial_s:_counter_i_reset) at %d",$time);
 end
#1 if (((_reg_19)===1'bx) || (1'b1)===1'bx) $display("hazard (_reg_19 || 1'b1) line 51 at %d\n",$time);
#1 if ((((_reg_17&(~_net_26)))===1'bx) || (1'b1)===1'bx) $display("hazard ((_reg_17&(~_net_26)) || 1'b1) line 54 at %d\n",$time);
#1 if (((_reg_14)===1'bx) || (1'b1)===1'bx) $display("hazard (_reg_14 || 1'b1) line 60 at %d\n",$time);
 end

// synthesis translate_on
// synopsys translate_on
   assign  _counter_i_reset = _reg_19|
    (_reg_17&(~_net_26))|
    _reg_14;
   assign  _counter_i_p_reset = p_reset;
   assign  _counter_i_m_clock = m_clock;
   assign  _net_9 = (start_send==1'b1);
   assign  _net_10 = 
// synthesis translate_off
// synopsys translate_off
(_net_9)? 
// synthesis translate_on
// synopsys translate_on
((_net_9)?(sending==1'b0):1'b0)
// synthesis translate_off
// synopsys translate_off
:1'bx
// synthesis translate_on
// synopsys translate_on
;
   assign  _net_21 = 
// synthesis translate_off
// synopsys translate_off
(_reg_13)? 
// synthesis translate_on
// synopsys translate_on
((_reg_13)?(~(_counter_i_f != 13'b1010001010000)):1'b0)
// synthesis translate_off
// synopsys translate_off
:1'bx
// synthesis translate_on
// synopsys translate_on
;

// synthesis translate_off
// synopsys translate_off
always @(posedge _reg_13_goto)
  begin
#1 if (_reg_13_goto===1'bx)
 begin
$display("Warning: control hazard(serial_s:_reg_13_goto) at %d",$time);
 end
#1 if (((((_reg_13&(~_net_21))&_net_22))===1'bx) || (1'b1)===1'bx) $display("hazard (((_reg_13&(~_net_21))&_net_22) || 1'b1) line 63 at %d\n",$time);
#1 if ((((_reg_13&_net_21))===1'bx) || (1'b1)===1'bx) $display("hazard ((_reg_13&_net_21) || 1'b1) line 63 at %d\n",$time);
 end

// synthesis translate_on
// synopsys translate_on
   assign  _reg_13_goto = ((_reg_13&(~_net_21))&_net_22)|
    (_reg_13&_net_21);

// synthesis translate_off
// synopsys translate_off
always @(posedge _reg_12_goin)
  begin
#1 if (_reg_12_goin===1'bx)
 begin
$display("Warning: control hazard(serial_s:_reg_12_goin) at %d",$time);
 end
#1 if ((((_reg_13&_net_21))===1'bx) || (1'b1)===1'bx) $display("hazard ((_reg_13&_net_21) || 1'b1) line 63 at %d\n",$time);
 end

// synthesis translate_on
// synopsys translate_on
   assign  _reg_12_goin = (_reg_13&_net_21);
   assign  _net_22 = 
// synthesis translate_off
// synopsys translate_off
((_reg_13&(~_net_21)))? 
// synthesis translate_on
// synopsys translate_on
(((_reg_13&(~_net_21)))?(_counter_i_f != 13'b1010001010000):1'b0)
// synthesis translate_off
// synopsys translate_off
:1'bx
// synthesis translate_on
// synopsys translate_on
;

// synthesis translate_off
// synopsys translate_off
always @(posedge _reg_13_goin)
  begin
#1 if (_reg_13_goin===1'bx)
 begin
$display("Warning: control hazard(serial_s:_reg_13_goin) at %d",$time);
 end
#1 if (((((_reg_13&(~_net_21))&_net_22))===1'bx) || (1'b1)===1'bx) $display("hazard (((_reg_13&(~_net_21))&_net_22) || 1'b1) line 63 at %d\n",$time);
 end

// synthesis translate_on
// synopsys translate_on
   assign  _reg_13_goin = ((_reg_13&(~_net_21))&_net_22);
   assign  _net_23 = 
// synthesis translate_off
// synopsys translate_off
(_reg_15)? 
// synthesis translate_on
// synopsys translate_on
((_reg_15)?(_net_6 < 4'b1001):1'b0)
// synthesis translate_off
// synopsys translate_off
:1'bx
// synthesis translate_on
// synopsys translate_on
;

// synthesis translate_off
// synopsys translate_off
always @(posedge _reg_15_goto)
  begin
#1 if (_reg_15_goto===1'bx)
 begin
$display("Warning: control hazard(serial_s:_reg_15_goto) at %d",$time);
 end
#1 if ((((_reg_15&_net_23))===1'bx) || (1'b1)===1'bx) $display("hazard ((_reg_15&_net_23) || 1'b1) line 59 at %d\n",$time);
 end

// synthesis translate_on
// synopsys translate_on
   assign  _reg_15_goto = (_reg_15&_net_23);

// synthesis translate_off
// synopsys translate_off
always @(posedge _reg_17_goin)
  begin
#1 if (_reg_17_goin===1'bx)
 begin
$display("Warning: control hazard(serial_s:_reg_17_goin) at %d",$time);
 end
#1 if ((((_reg_15&_net_23))===1'bx) || (1'b1)===1'bx) $display("hazard ((_reg_15&_net_23) || 1'b1) line 59 at %d\n",$time);
 end

// synthesis translate_on
// synopsys translate_on
   assign  _reg_17_goin = (_reg_15&_net_23);
   assign  _net_24 = 
// synthesis translate_off
// synopsys translate_off
(_reg_16)? 
// synthesis translate_on
// synopsys translate_on
((_reg_16)?(~(_counter_i_f != 13'b1010001010000)):1'b0)
// synthesis translate_off
// synopsys translate_off
:1'bx
// synthesis translate_on
// synopsys translate_on
;

// synthesis translate_off
// synopsys translate_off
always @(posedge _reg_16_goto)
  begin
#1 if (_reg_16_goto===1'bx)
 begin
$display("Warning: control hazard(serial_s:_reg_16_goto) at %d",$time);
 end
#1 if (((((_reg_16&(~_net_24))&_net_25))===1'bx) || (1'b1)===1'bx) $display("hazard (((_reg_16&(~_net_24))&_net_25) || 1'b1) line 57 at %d\n",$time);
#1 if ((((_reg_16&_net_24))===1'bx) || (1'b1)===1'bx) $display("hazard ((_reg_16&_net_24) || 1'b1) line 57 at %d\n",$time);
 end

// synthesis translate_on
// synopsys translate_on
   assign  _reg_16_goto = ((_reg_16&(~_net_24))&_net_25)|
    (_reg_16&_net_24);

// synthesis translate_off
// synopsys translate_off
always @(posedge _reg_15_goin)
  begin
#1 if (_reg_15_goin===1'bx)
 begin
$display("Warning: control hazard(serial_s:_reg_15_goin) at %d",$time);
 end
#1 if ((((_reg_16&_net_24))===1'bx) || (1'b1)===1'bx) $display("hazard ((_reg_16&_net_24) || 1'b1) line 57 at %d\n",$time);
 end

// synthesis translate_on
// synopsys translate_on
   assign  _reg_15_goin = (_reg_16&_net_24);
   assign  _net_25 = 
// synthesis translate_off
// synopsys translate_off
((_reg_16&(~_net_24)))? 
// synthesis translate_on
// synopsys translate_on
(((_reg_16&(~_net_24)))?(_counter_i_f != 13'b1010001010000):1'b0)
// synthesis translate_off
// synopsys translate_off
:1'bx
// synthesis translate_on
// synopsys translate_on
;

// synthesis translate_off
// synopsys translate_off
always @(posedge _reg_16_goin)
  begin
#1 if (_reg_16_goin===1'bx)
 begin
$display("Warning: control hazard(serial_s:_reg_16_goin) at %d",$time);
 end
#1 if (((((_reg_16&(~_net_24))&_net_25))===1'bx) || (1'b1)===1'bx) $display("hazard (((_reg_16&(~_net_24))&_net_25) || 1'b1) line 57 at %d\n",$time);
 end

// synthesis translate_on
// synopsys translate_on
   assign  _reg_16_goin = ((_reg_16&(~_net_24))&_net_25);
   assign  _net_26 = 
// synthesis translate_off
// synopsys translate_off
(_reg_17)? 
// synthesis translate_on
// synopsys translate_on
((_reg_17)?(~(loop < 4'b1001)):1'b0)
// synthesis translate_off
// synopsys translate_off
:1'bx
// synthesis translate_on
// synopsys translate_on
;

// synthesis translate_off
// synopsys translate_off
always @(posedge _reg_17_goto)
  begin
#1 if (_reg_17_goto===1'bx)
 begin
$display("Warning: control hazard(serial_s:_reg_17_goto) at %d",$time);
 end
#1 if ((((_reg_17&_net_26))===1'bx) || (1'b1)===1'bx) $display("hazard ((_reg_17&_net_26) || 1'b1) line 59 at %d\n",$time);
 end

// synthesis translate_on
// synopsys translate_on
   assign  _reg_17_goto = (_reg_17&_net_26);

// synthesis translate_off
// synopsys translate_off
always @(posedge _reg_14_goin)
  begin
#1 if (_reg_14_goin===1'bx)
 begin
$display("Warning: control hazard(serial_s:_reg_14_goin) at %d",$time);
 end
#1 if ((((_reg_17&_net_26))===1'bx) || (1'b1)===1'bx) $display("hazard ((_reg_17&_net_26) || 1'b1) line 59 at %d\n",$time);
 end

// synthesis translate_on
// synopsys translate_on
   assign  _reg_14_goin = (_reg_17&_net_26);
   assign  TDX = TDX_r;
always @(posedge m_clock or posedge p_reset)
  begin
if (p_reset)
     TDX_r <= 1'b1;
else 
// synthesis translate_off
// synopsys translate_off
if ((_reg_15&_reg_12))   TDX_r <= 1'bx; 
  else 
// synthesis translate_on
// synopsys translate_on
if (_reg_15)
      TDX_r <= (data[loop]);
else if (_reg_12)
      TDX_r <= 1'b1;
end

// synthesis translate_off
// synopsys translate_off
always @(posedge m_clock)
  begin
if (((_reg_15|_reg_12)==1'b1) ||
 ((_reg_15|_reg_12)==1'b0) ) begin
 if ((_reg_15&_reg_12))
 begin $display("Warning: assign collision(serial_s:TDX_r) at %d",$time);

  end
 end
 else 
 $display("Warning: register set hazard(serial_s:TDX_r) at %d",$time);

  end

// synthesis translate_on
// synopsys translate_on
always @(posedge m_clock or posedge p_reset)
  begin
if (p_reset)
     sending <= 1'b0;
else 
// synthesis translate_off
// synopsys translate_off
if (((send|_reg_20)&_reg_11))   sending <= 1'bx; 
  else 
// synthesis translate_on
// synopsys translate_on
if ((send|_reg_20))
      sending <= 1'b1;
else if (_reg_11)
      sending <= 1'b0;
end

// synthesis translate_off
// synopsys translate_off
always @(posedge m_clock)
  begin
if ((((send|_reg_20)|_reg_11)==1'b1) ||
 (((send|_reg_20)|_reg_11)==1'b0) ) begin
 if (((send|_reg_20)&_reg_11))
 begin $display("Warning: assign collision(serial_s:sending) at %d",$time);

  end
 end
 else 
 $display("Warning: register set hazard(serial_s:sending) at %d",$time);

  end

// synthesis translate_on
// synopsys translate_on
always @(posedge m_clock)
  begin
if ((_net_9&_net_10))
      data <= 9'b010000010;
end
always @(posedge m_clock or posedge p_reset)
  begin
if (p_reset)
     loop <= 4'b0000;
else 
// synthesis translate_off
// synopsys translate_off
if ((_reg_18&_reg_15))   loop <= 4'bx; 
  else 
// synthesis translate_on
// synopsys translate_on
if (_reg_18)
      loop <= 4'b0000;
else if (_reg_15)
      loop <= _net_6;
end

// synthesis translate_off
// synopsys translate_off
always @(posedge m_clock)
  begin
if (((_reg_18|_reg_15)==1'b1) ||
 ((_reg_18|_reg_15)==1'b0) ) begin
 if ((_reg_18&_reg_15))
 begin $display("Warning: assign collision(serial_s:loop) at %d",$time);

  end
 end
 else 
 $display("Warning: register set hazard(serial_s:loop) at %d",$time);

  end

// synthesis translate_on
// synopsys translate_on
always @(posedge m_clock or posedge p_reset)
  begin
if (p_reset)
     _reg_11 <= 1'b0;
else if ((_reg_11|_reg_12))
      _reg_11 <= _reg_12;
end
always @(posedge m_clock or posedge p_reset)
  begin
if (p_reset)
     _reg_12 <= 1'b0;
else if (((_reg_13&_net_21)|(_reg_12|_reg_13)))
      _reg_12 <= ((_reg_13&_net_21)|(_reg_13&(~_reg_13_goto)));
end
always @(posedge m_clock or posedge p_reset)
  begin
if (p_reset)
     _reg_13 <= 1'b0;
else if ((((_reg_13&(~_net_21))&_net_22)|(_reg_13|_reg_14)))
      _reg_13 <= (((_reg_13&(~_net_21))&_net_22)|_reg_14);
end
always @(posedge m_clock or posedge p_reset)
  begin
if (p_reset)
     _reg_14 <= 1'b0;
else if (((_reg_17&_net_26)|(_reg_14|_reg_15)))
      _reg_14 <= ((_reg_17&_net_26)|(_reg_15&(~_reg_15_goto)));
end
always @(posedge m_clock or posedge p_reset)
  begin
if (p_reset)
     _reg_15 <= 1'b0;
else if (((_reg_16&_net_24)|(_reg_15|_reg_16)))
      _reg_15 <= ((_reg_16&_net_24)|(_reg_16&(~_reg_16_goto)));
end
always @(posedge m_clock or posedge p_reset)
  begin
if (p_reset)
     _reg_16 <= 1'b0;
else if ((((_reg_16&(~_net_24))&_net_25)|(_reg_16|_reg_17)))
      _reg_16 <= (((_reg_16&(~_net_24))&_net_25)|(_reg_17&(~_reg_17_goto)));
end
always @(posedge m_clock or posedge p_reset)
  begin
if (p_reset)
     _reg_17 <= 1'b0;
else if (((_reg_15&_net_23)|(_reg_17|_reg_18)))
      _reg_17 <= ((_reg_15&_net_23)|_reg_18);
end
always @(posedge m_clock or posedge p_reset)
  begin
if (p_reset)
     _reg_18 <= 1'b0;
else if ((_reg_18|_reg_19))
      _reg_18 <= _reg_19;
end
always @(posedge m_clock or posedge p_reset)
  begin
if (p_reset)
     _reg_19 <= 1'b0;
else if ((send|(_reg_19|_reg_20)))
      _reg_19 <= (_reg_20|send);
end
always @(posedge m_clock or posedge p_reset)
  begin
if (p_reset)
     _reg_20 <= 1'b0;
else if (_reg_20)
      _reg_20 <= 1'b0;
end
endmodule
/*
 Produced by NSL Core(version=20151214), IP ARCH, Inc. Sat May 14 10:23:53 2016
 Licensed to :EVALUATION USER
*/

test07_max10/testbench.v
`timescale 1ns/1ns

module testbench;
  reg p_reset, m_clock, start_send;
  wire TDX;

  initial begin
    $dumpfile("testbench.vcd");
    $dumpvars(0, testbench);
    m_clock = 0;
    start_send = 0;
    p_reset = 1;
    #100
    p_reset = 0;
    #100
    #100
    start_send = 1;
    #20
    start_send = 0;
    #1000000
    $finish;
  end

  always #10 begin
    m_clock = ~m_clock;
  end
  serial_s serial_s (
    .p_reset(p_reset),
    .m_clock(m_clock),
    .start_send(start_send),
    .TDX(TDX)
  );
endmodule

test07_max10/testbench.vcd
$date
	Sat May 14 10:24:36 2016
$end
$version
	Icarus Verilog
$end
$timescale
	1ns
$end
$scope module testbench $end
$var wire 1 ! TDX $end
$var reg 1 " m_clock $end
$var reg 1 # p_reset $end
$var reg 1 $ start_send $end
$scope module serial_s $end
$var wire 1 ! TDX $end
$var wire 1 % _counter_i_countup $end
$var wire 1 & _counter_i_m_clock $end
$var wire 1 ' _counter_i_p_reset $end
$var wire 1 ( _counter_i_reset $end
$var wire 1 ) _net_9 $end
$var wire 1 * _reg_12_goin $end
$var wire 1 + _reg_13_goin $end
$var wire 1 , _reg_13_goto $end
$var wire 1 - _reg_14_goin $end
$var wire 1 . _reg_15_goin $end
$var wire 1 / _reg_15_goto $end
$var wire 1 0 _reg_16_goin $end
$var wire 1 1 _reg_16_goto $end
$var wire 1 2 _reg_17_goin $end
$var wire 1 3 _reg_17_goto $end
$var wire 1 " m_clock $end
$var wire 1 # p_reset $end
$var wire 1 4 send $end
$var wire 1 $ start_send $end
$var wire 4 5 _net_6 [3:0] $end
$var wire 1 6 _net_26 $end
$var wire 1 7 _net_25 $end
$var wire 1 8 _net_24 $end
$var wire 1 9 _net_23 $end
$var wire 1 : _net_22 $end
$var wire 1 ; _net_21 $end
$var wire 1 < _net_10 $end
$var wire 13 = _counter_i_f [12:0] $end
$var reg 1 > TDX_r $end
$var reg 1 ? _reg_11 $end
$var reg 1 @ _reg_12 $end
$var reg 1 A _reg_13 $end
$var reg 1 B _reg_14 $end
$var reg 1 C _reg_15 $end
$var reg 1 D _reg_16 $end
$var reg 1 E _reg_17 $end
$var reg 1 F _reg_18 $end
$var reg 1 G _reg_19 $end
$var reg 1 H _reg_20 $end
$var reg 9 I data [8:0] $end
$var reg 4 J loop [3:0] $end
$var reg 1 K sending $end
$scope module counter_i $end
$var wire 1 % countup $end
$var wire 13 L f [12:0] $end
$var wire 1 " m_clock $end
$var wire 1 # p_reset $end
$var wire 1 ( reset $end
$var wire 1 M _net_1 $end
$var wire 1 N _net_0 $end
$var reg 13 O cnt [12:0] $end
$upscope $end
$upscope $end
$upscope $end
$enddefinitions $end
#0
$dumpvars
b0 O
xN
xM
b0 L
0K
b0 J
bx I
0H
0G
0F
0E
0D
0C
0B
0A
0@
0?
1>
b0 =
x<
x;
x:
x9
x8
x7
x6
bx 5
04
03
02
01
00
0/
0.
0-
0,
0+
0*
0)
0(
1'
0&
0%
0$
1#
0"
1!
$end
#10
1&
1"
#20
0&
0"
#30
1&
1"
#40
0&
0"
#50
1&
1"
#60
0&
0"
#70
1&
1"
#80
0&
0"
#90
1&
1"
#100
0&
0"
0'
0#
#110
1&
1"
#120
0&
0"
#130
1&
1"
#140
0&
0"
#150
1&
1"
#160
0&
0"
#170
1&
1"
#180
0&
0"
#190
1&
1"
#200
0&
0"
#210
1&
1"
#220
0&
0"
#230
1&
1"
#240
0&
0"
#250
1&
1"
#260
0&
0"
#270
1&
1"
#280
0&
0"
#290
1&
1"
#300
1<
14
1)
0&
0"
1$
#310
04
0<
1(
b10000010 I
1K
1G
1&
1"
#320
x<
0)
0&
0"
0$
#330
0(
0G
1F
1&
1"
#340
0&
0"
#350
1(
06
0-
03
1E
0F
1&
1"
#360
0&
0"
#370
1N
17
0M
0(
10
11
1%
x6
08
0.
0E
1D
1&
1"
#380
0&
0"
#390
b1 =
b1 L
b1 O
1&
1"
#400
0&
0"
#410
b10 =
b10 L
b10 O
1&
1"
#420
0&
0"
#430
b11 =
b11 L
b11 O
1&
1"
#440
0&
0"
#450
b100 =
b100 L
b100 O
1&
1"
#460
0&
0"
#470
b101 =
b101 L
b101 O
1&
1"
#480
0&
0"
#490
b110 =
b110 L
b110 O
1&
1"
#500
0&
0"
#510
b111 =
b111 L
b111 O
1&
1"
#520
0&
0"
#530
b1000 =
b1000 L
b1000 O
1&
1"
#540
0&
0"
#550
b1001 =
b1001 L
b1001 O
1&
1"
#560
0&
0"
#570
b1010 =
b1010 L
b1010 O
1&
1"
#580
0&
0"
#590
b1011 =
b1011 L
b1011 O
1&
1"
#600
0&
0"
#610
b1100 =
b1100 L
b1100 O
1&
1"
#620
0&
0"
#630
b1101 =
b1101 L
b1101 O
1&
1"
#640
0&
0"
#650
b1110 =
b1110 L
b1110 O
1&
1"
#660
0&
0"
#670
b1111 =
b1111 L
b1111 O
1&
1"
#680
0&
0"
#690
b10000 =
b10000 L
b10000 O
1&
1"
#700
0&
0"
#710
b10001 =
b10001 L
b10001 O
1&
1"
#720
0&
0"
#730
b10010 =
b10010 L
b10010 O
1&
1"
#740
0&
0"
#750
b10011 =
b10011 L
b10011 O
1&
1"
#760
0&
0"
#770
b10100 =
b10100 L
b10100 O
1&
1"
#780
0&
0"
#790
b10101 =
b10101 L
b10101 O
1&
1"
#800
0&
0"
#810
b10110 =
b10110 L
b10110 O
1&
1"
#820
0&
0"
#830
b10111 =
b10111 L
b10111 O
1&
1"
#840
0&
0"
#850
b11000 =
b11000 L
b11000 O
1&
1"
#860
0&
0"
#870
b11001 =
b11001 L
b11001 O
1&
1"
#880
0&
0"
#890
b11010 =
b11010 L
b11010 O
1&
1"
#900
0&
0"
#910
b11011 =
b11011 L
b11011 O
1&
1"
#920
0&
0"
#930
b11100 =
b11100 L
b11100 O
1&
1"
#940
0&
0"
#950
b11101 =
b11101 L
b11101 O
1&
1"
#960
0&
0"
#970
b11110 =
b11110 L
b11110 O
1&
1"
#980
0&
0"
#990
b11111 =
b11111 L
b11111 O
1&
1"
#1000
0&
0"
#1010
b100000 =
b100000 L
b100000 O
1&
1"
#1020
0&
0"
#1030
b100001 =
b100001 L
b100001 O
1&
1"
#1040
0&
0"
#1050
b100010 =
b100010 L
b100010 O
1&
1"
#1060
0&
0"
#1070
b100011 =
b100011 L
b100011 O
1&
1"
#1080
0&
0"
#1090
b100100 =
b100100 L
b100100 O
1&
1"
#1100
0&
0"
#1110
b100101 =
b100101 L
b100101 O
1&
1"
#1120
0&
0"
#1130
b100110 =
b100110 L
b100110 O
1&
1"
#1140
0&
0"
#1150
b100111 =
b100111 L
b100111 O
1&
1"
#1160
0&
0"
#1170
b101000 =
b101000 L
b101000 O
1&
1"
#1180
0&
0"
#1190
b101001 =
b101001 L
b101001 O
1&
1"
#1200
0&
0"
#1210
b101010 =
b101010 L
b101010 O
1&
1"
#1220
0&
0"
#1230
b101011 =
b101011 L
b101011 O
1&
1"
#1240
0&
0"
#1250
b101100 =
b101100 L
b101100 O
1&
1"
#1260
0&
0"
#1270
b101101 =
b101101 L
b101101 O
1&
1"
#1280
0&
0"
#1290
b101110 =
b101110 L
b101110 O
1&
1"
#1300
0&
0"
#1310
b101111 =
b101111 L
b101111 O
1&
1"
#1320
0&
0"
#1330
b110000 =
b110000 L
b110000 O
1&
1"
#1340
0&
0"
#1350
b110001 =
b110001 L
b110001 O
1&
1"
#1360
0&
0"
#1370
b110010 =
b110010 L
b110010 O
1&
1"
#1380
0&
0"
#1390
b110011 =
b110011 L
b110011 O
1&
1"
#1400
0&
0"
#1410
b110100 =
b110100 L
b110100 O
1&
1"
#1420
0&
0"
#1430
b110101 =
b110101 L
b110101 O
1&
1"
#1440
0&
0"
#1450
b110110 =
b110110 L
b110110 O
1&
1"
#1460
0&
0"
#1470
b110111 =
b110111 L
b110111 O
1&
1"
#1480
0&
0"
#1490
b111000 =
b111000 L
b111000 O
1&
1"
#1500
0&
0"
#1510
b111001 =
b111001 L
b111001 O
1&
1"
#1520
0&
0"
#1530
b111010 =
b111010 L
b111010 O
1&
1"
#1540
0&
0"
#1550
b111011 =
b111011 L
b111011 O
1&
1"
#1560
0&
0"
#1570
b111100 =
b111100 L
b111100 O
1&
1"
#1580
0&
0"
#1590
b111101 =
b111101 L
b111101 O
1&
1"
#1600
0&
0"
#1610
b111110 =
b111110 L
b111110 O
1&
1"
#1620
0&
0"
#1630
b111111 =
b111111 L
b111111 O
1&
1"
#1640
0&
0"
#1650
b1000000 =
b1000000 L
b1000000 O
1&
1"
#1660
0&
0"
#1670
b1000001 =
b1000001 L
b1000001 O
1&
1"
#1680
0&
0"
#1690
b1000010 =
b1000010 L
b1000010 O
1&
1"
#1700
0&
0"
#1710
b1000011 =
b1000011 L
b1000011 O
1&
1"
#1720
0&
0"
#1730
b1000100 =
b1000100 L
b1000100 O
1&
1"
#1740
0&
0"
#1750
b1000101 =
b1000101 L
b1000101 O
1&
1"
#1760
0&
0"
#1770
b1000110 =
b1000110 L
b1000110 O
1&
1"
#1780
0&
0"
#1790
b1000111 =
b1000111 L
b1000111 O
1&
1"
#1800
0&
0"
#1810
b1001000 =
b1001000 L
b1001000 O
1&
1"
#1820
0&
0"
#1830
b1001001 =
b1001001 L
b1001001 O
1&
1"
#1840
0&
0"
#1850
b1001010 =
b1001010 L
b1001010 O
1&
1"
#1860
0&
0"
#1870
b1001011 =
b1001011 L
b1001011 O
1&
1"
#1880
0&
0"
#1890
b1001100 =
b1001100 L
b1001100 O
1&
1"
#1900
0&
0"
#1910
b1001101 =
b1001101 L
b1001101 O
1&
1"
#1920
0&
0"
#1930
b1001110 =
b1001110 L
b1001110 O
1&
1"
#1940
0&
0"
#1950
b1001111 =
b1001111 L
b1001111 O
1&
1"
#1960
0&
0"
#1970
b1010000 =
b1010000 L
b1010000 O
1&
1"
#1980
0&
0"
#1990
b1010001 =
b1010001 L
b1010001 O
1&
1"
#2000
0&
0"
#2010
b1010010 =
b1010010 L
b1010010 O
1&
1"
#2020
0&
0"
#2030
b1010011 =
b1010011 L
b1010011 O
1&
1"
#2040
0&
0"
#2050
b1010100 =
b1010100 L
b1010100 O
1&
1"
#2060
0&
0"
#2070
b1010101 =
b1010101 L
b1010101 O
1&
1"
#2080
0&
0"
#2090
b1010110 =
b1010110 L
b1010110 O
1&
1"
#2100
0&
0"
#2110
b1010111 =
b1010111 L
b1010111 O
1&
1"
#2120
0&
0"
#2130
b1011000 =
b1011000 L
b1011000 O
1&
1"
#2140
0&
0"
#2150
b1011001 =
b1011001 L
b1011001 O
1&
1"
#2160
0&
0"
#2170
b1011010 =
b1011010 L
b1011010 O
1&
1"
#2180
0&
0"
#2190
b1011011 =
b1011011 L
b1011011 O
1&
1"
#2200
0&
0"
#2210
b1011100 =
b1011100 L
b1011100 O
1&
1"
#2220
0&
0"
#2230
b1011101 =
b1011101 L
b1011101 O
1&
1"
#2240
0&
0"
#2250
b1011110 =
b1011110 L
b1011110 O
1&
1"
#2260
0&
0"
#2270
b1011111 =
b1011111 L
b1011111 O
1&
1"
#2280
0&
0"
#2290
b1100000 =
b1100000 L
b1100000 O
1&
1"
#2300
0&
0"
#2310
b1100001 =
b1100001 L
b1100001 O
1&
1"
#2320
0&
0"
#2330
b1100010 =
b1100010 L
b1100010 O
1&
1"
#2340
0&
0"
#2350
b1100011 =
b1100011 L
b1100011 O
1&
1"
#2360
0&
0"
#2370
b1100100 =
b1100100 L
b1100100 O
1&
1"
#2380
0&
0"
#2390
b1100101 =
b1100101 L
b1100101 O
1&
1"
#2400
0&
0"
#2410
b1100110 =
b1100110 L
b1100110 O
1&
1"
#2420
0&
0"
#2430
b1100111 =
b1100111 L
b1100111 O
1&
1"
#2440
0&
0"
#2450
b1101000 =
b1101000 L
b1101000 O
1&
1"
#2460
0&
0"
#2470
b1101001 =
b1101001 L
b1101001 O
1&
1"
#2480
0&
0"
#2490
b1101010 =
b1101010 L
b1101010 O
1&
1"
#2500
0&
0"
#2510
b1101011 =
b1101011 L
b1101011 O
1&
1"
#2520
0&
0"
#2530
b1101100 =
b1101100 L
b1101100 O
1&
1"
#2540
0&
0"
#2550
b1101101 =
b1101101 L
b1101101 O
1&
1"
#2560
0&
0"
