test06/test01.v

`timescale	1ns / 1ns
`default_nettype none

/*
 Produced by NSL Core(version=20151214), IP ARCH, Inc. Mon Mar 28 13:06:33 2016
 Licensed to :EVALUATION USER
*/

// synthesis translate_off
// synopsys translate_off
/*
 DO NOT USE ANY PART OF THIS FILE FOR COMMERCIAL PRODUCTS. 
*/

module test01 ( p_reset , m_clock );
  input p_reset, m_clock;
  wire p_reset, m_clock;
  reg [7:0] r;
  reg [7:0] a;
  reg b;
  reg start;
  wire _proc_start_set;
  wire _proc_start_reset;
  wire _net_0;
  reg _reg_1;
  reg _reg_2;
  reg _reg_3;
  reg _reg_4;
  reg _reg_5;
  reg _reg_6;
  reg _reg_7;

always @(posedge _proc_start_set)
  begin
#1 if (_proc_start_set===1'bx)
 begin
$display("Warning: control hazard(test01:_proc_start_set) at %d",$time);
 end
#1 if (((_net_0)===1'bx) || (1'b1)===1'bx) $display("hazard (_net_0 || 1'b1) line 10 at %d\n",$time);
 end
   assign  _proc_start_set = _net_0;
always @(posedge _proc_start_reset)
  begin
#1 if (_proc_start_reset===1'bx)
 begin
$display("Warning: control hazard(test01:_proc_start_reset) at %d",$time);
 end
#1 if ((((_reg_1&start))===1'bx) || (1'b1)===1'bx) $display("hazard ((_reg_1&start) || 1'b1) line 24 at %d\n",$time);
 end
   assign  _proc_start_reset = (_reg_1&start);
   assign  _net_0 = (r==8'b00000000);
always @(posedge m_clock)
  begin
    if((_reg_2&start))
    begin
    $display("%d",a);
    end
  end
always @(posedge m_clock)
  begin
    if((_reg_4&start))
    begin
    $display("%d",a);
    end
  end
always @(posedge m_clock)
  begin
    if((_reg_6&start))
    begin
    $display("%d",a);
    end
  end
always @(posedge m_clock or posedge p_reset)
  begin
if (p_reset)
     r <= 8'b00000000;
else if (_net_0)
      r <= 8'b00001010;
end
always @(posedge m_clock)
  begin
if ((((start&_reg_7)&(_reg_5&start))|(((start&_reg_7)|(_reg_5&start))&(_reg_3&start))))   a <= 8'bx; 
  else if ((start&_reg_7))
      a <= 8'b00000000;
else if ((_reg_5&start))
      a <= 8'b00001010;
else if ((_reg_3&start))
      a <= (a>>1);
end
always @(posedge m_clock)
  begin
if (((((start&_reg_7)|(_reg_5&start))|(_reg_3&start))==1'b1) ||
 ((((start&_reg_7)|(_reg_5&start))|(_reg_3&start))==1'b0) ) begin
 if ((((start&_reg_7)&(_reg_5&start))|(((start&_reg_7)|(_reg_5&start))&(_reg_3&start))))
 begin $display("Warning: assign collision(test01:a) at %d",$time);

  end
 end
 else 
 $display("Warning: register set hazard(test01:a) at %d",$time);

  end
always @(posedge m_clock or posedge p_reset)
  begin
if (p_reset)
     b <= 1'b0;
else   b <= (~b);
end
always @(posedge m_clock or posedge p_reset)
  begin
if (p_reset)
     start <= 1'b0;
else if ((_proc_start_set|_proc_start_reset))
      start <= _proc_start_set;
end
always @(posedge m_clock or posedge p_reset)
  begin
if (p_reset)
     _reg_1 <= 1'b0;
else if ((_proc_start_reset|(_reg_1|_reg_2)))
      _reg_1 <= (_reg_2&(~_proc_start_reset));
end
always @(posedge m_clock or posedge p_reset)
  begin
if (p_reset)
     _reg_2 <= 1'b0;
else if ((_proc_start_reset|(_reg_2|_reg_3)))
      _reg_2 <= (_reg_3&(~_proc_start_reset));
end
always @(posedge m_clock or posedge p_reset)
  begin
if (p_reset)
     _reg_3 <= 1'b0;
else if ((_proc_start_reset|(_reg_3|_reg_4)))
      _reg_3 <= (_reg_4&(~_proc_start_reset));
end
always @(posedge m_clock or posedge p_reset)
  begin
if (p_reset)
     _reg_4 <= 1'b0;
else if ((_proc_start_reset|(_reg_4|_reg_5)))
      _reg_4 <= (_reg_5&(~_proc_start_reset));
end
always @(posedge m_clock or posedge p_reset)
  begin
if (p_reset)
     _reg_5 <= 1'b0;
else if ((_proc_start_reset|(_reg_5|_reg_6)))
      _reg_5 <= (_reg_6&(~_proc_start_reset));
end
always @(posedge m_clock or posedge p_reset)
  begin
if (p_reset)
     _reg_6 <= 1'b0;
else if ((_proc_start_reset|(_reg_7|(_reg_6|_reg_7))))
      _reg_6 <= (_reg_7&(~_proc_start_reset));
end
always @(posedge m_clock or posedge p_reset)
  begin
if (p_reset)
     _reg_7 <= 1'b0;
else if (((_proc_start_set|_proc_start_reset)|_reg_7))
      _reg_7 <= _proc_start_set;
end
endmodule

// synthesis translate_on
// synopsys translate_on
/*
 Produced by NSL Core(version=20151214), IP ARCH, Inc. Mon Mar 28 13:06:33 2016
 Licensed to :EVALUATION USER
*/
/*
 Produced by NSL Core(version=20151214), IP ARCH, Inc. Mon Mar 28 13:06:33 2016
 Licensed to :EVALUATION USER:
*/

//synthesis translate_off
/*
 DO NOT USE ANY PART OF THIS FILE FOR COMMERCIAL PRODUCTS. 
*/
module tb;
	parameter tCYC=2;
	parameter tPD=(tCYC/10);

	reg p_reset;
	reg m_clock;

	test01 test01_instance(
		.p_reset(p_reset),
		.m_clock(m_clock)
	);

	initial forever #(tCYC/2) m_clock = ~m_clock;

	initial begin
		$dumpfile("test01.vcd");
		$dumpvars(0,test01_instance);
	end

	initial begin
		#(tPD)
			p_reset = 1;
			m_clock = 0;
		#(tCYC)
			p_reset = 0;
	end

endmodule

//synthesis translate_on

test06/test01.vcd
$date
	Mon Mar 28 13:06:55 2016
$end
$version
	Icarus Verilog
$end
$timescale
	1ns
$end
$scope module tb $end
$scope module test01_instance $end
$var wire 1 ! _proc_start_reset $end
$var wire 1 " _proc_start_set $end
$var wire 1 # m_clock $end
$var wire 1 $ p_reset $end
$var wire 1 % _net_0 $end
$var reg 1 & _reg_1 $end
$var reg 1 ' _reg_2 $end
$var reg 1 ( _reg_3 $end
$var reg 1 ) _reg_4 $end
$var reg 1 * _reg_5 $end
$var reg 1 + _reg_6 $end
$var reg 1 , _reg_7 $end
$var reg 8 - a [7:0] $end
$var reg 1 . b $end
$var reg 8 / r [7:0] $end
$var reg 1 0 start $end
$upscope $end
$upscope $end
$enddefinitions $end
#0
$dumpvars
00
b0 /
0.
bx -
0,
0+
0*
0)
0(
0'
0&
1%
1$
0#
1"
0!
$end
#1
1#
#2
0#
0$
#3
0"
0%
b1010 /
1.
10
1,
1#
#4
0#
#5
0,
1+
0.
b0 -
1#
#6
0#
#7
1.
1*
0+
1#
#8
0#
#9
0*
1)
0.
b1010 -
1#
#10
0#
#11
1.
1(
0)
1#
#12
0#
#13
0(
1'
0.
b101 -
1#
#14
0#
#15
1!
1.
1&
0'
1#
#16
0#
#17
0!
0&
00
0.
1#
#18
0#
#19
1.
1#
#20
0#
#21
0.
1#
#22
0#
#23
1.
1#
#24
0#
#25
0.
1#
#26
0#
#27
1.
1#
#28
0#
#29
0.
1#
#30
0#
#31
1.
1#
#32
0#
#33
0.
1#
#34
0#
#35
1.
1#
#36
0#
#37
0.
1#
#38
0#
#39
1.
1#
#40
0#
#41
0.
1#
#42
0#
#43
1.
1#
#44
0#
#45
0.
1#
#46
0#
#47
1.
1#
#48
0#
#49
0.
1#
#50
0#
#51
1.
1#
#52
0#
#53
0.
1#
#54
0#
#55
1.
1#
#56
0#
#57
0.
1#
#58
0#
#59
1.
1#
#60
0#
#61
0.
1#
#62
0#
#63
1.
1#
#64
0#
#65
0.
1#
#66
0#
#67
1.
1#
#68
0#
#69
0.
1#
#70
0#
#71
1.
1#
#72
0#
#73
0.
1#
#74
0#
#75
1.
1#
#76
0#
#77
0.
1#
#78
0#
#79
1.
1#
#80
0#
#81
0.
1#
#82
0#
#83
1.
1#
#84
0#
#85
0.
1#
#86
0#
#87
1.
1#
#88
0#
#89
0.
1#
#90
0#
#91
1.
1#
#92
0#
#93
0.
1#
#94
0#
#95
1.
1#
#96
0#
#97
0.
1#
#98
0#
#99
1.
1#
#100
0#
#101
0.
1#
#102
0#
#103
1.
1#
#104
0#
#105
0.
1#
#106
0#
#107
1.
1#
#108
0#
#109
0.
1#
#110
0#
#111
1.
1#
#112
0#
#113
0.
1#
#114
0#
#115
1.
1#
#116
0#
#117
0.
1#
#118
0#
#119
1.
1#
#120
0#
#121
0.
1#
#122
0#
#123
1.
1#
#124
0#
#125
0.
1#
#126
0#
#127
1.
1#
#128
0#
#129
0.
1#
#130
0#
#131
1.
1#
#132
0#
#133
0.
1#
#134
0#
#135
1.
1#
#136
0#
#137
0.
1#
#138
0#
#139
1.
1#
#140
0#
#141
0.
1#
#142
0#
#143
1.
1#
#144
0#
#145
0.
1#
#146
0#
#147
1.
1#
#148
0#
#149
0.
1#
#150
0#
#151
1.
1#
#152
0#
#153
0.
1#
#154
0#
#155
1.
1#
#156
0#
#157
0.
1#
#158
0#
#159
1.
1#
#160
0#
#161
0.
1#
#162
0#
#163
1.
1#
#164
0#
#165
0.
1#
#166
0#
#167
1.
1#
#168
0#
#169
0.
1#
#170
0#
#171
1.
1#
#172
0#
#173
0.
1#
#174
0#
#175
1.
1#
#176
0#
#177
0.
1#
#178
0#
#179
1.
1#
#180
0#
#181
0.
1#
#182
0#
#183
1.
1#
#184
0#
#185
0.
1#
#186
0#
#187
1.
1#
#188
0#
#189
0.
1#
#190
0#
#191
1.
1#
#192
0#
#193
0.
1#
#194
0#
#195
1.
1#
#196
0#
#197
0.
1#
#198
0#
#199
1.
1#
#200
0#
#201
0.
1#
#202
0#
#203
1.
1#
#204
0#
#205
0.
1#
#206
0#
#207
1.
1#
#208
0#
#209
0.
1#
#210
0#
#211
1.
1#
#212
0#
#213
0.
1#
#214
0#
#215
1.
1#
#216
0#
#217
0.
1#
#218
0#
#219
1.
1#
#220
0#
#221
0.
1#
#222
0#
#223
1.
1#
#224
0#
#225
0.
1#
#226
0#
#227
1.
1#
#228
0#
#229
0.
1#
#230
0#
#231
1.
1#
#232
0#
#233
0.
1#
#234
0#
#235
1.
1#
#236
0#
#237
0.
1#
#238
0#
#239
1.
1#
#240
0#
#241
0.
1#
#242
0#
#243
1.
1#
#244
0#
#245
0.
1#
#246
0#
#247
1.
1#
#248
0#
#249
0.
1#
#250
0#
#251
1.
1#
#252
0#
#253
0.
1#
#254
0#
#255
1.
1#
#256
0#
#257
0.
1#
#258
0#
#259
1.
1#
#260
0#
#261
0.
1#
#262
0#
#263
1.
1#
#264
0#
#265
0.
1#
#266
0#
#267
1.
1#
#268
0#
#269
0.
1#
#270
0#
#271
1.
1#
#272
0#
#273
0.
1#
#274
0#
#275
1.
1#
#276
0#
#277
0.
1#
#278
0#
#279
1.
1#
#280
0#
#281
0.
1#
#282
0#
#283
1.
1#
#284
0#
#285
0.
1#
#286
0#
#287
1.
1#
#288
0#
#289
0.
1#
#290
0#
#291
1.
1#
#292
0#
#293
0.
1#
#294
0#
#295
1.
1#
#296
0#
#297
0.
1#
#298
0#
#299
1.
1#
#300
0#
#301
0.
1#
#302
0#
#303
1.
1#
#304
0#
#305
0.
1#
#306
0#
#307
1.
1#
#308
0#
#309
0.
1#
#310
0#
#311
1.
1#
#312
0#
#313
0.
1#
#314
0#
#315
1.
1#
#316
0#
#317
0.
1#
#318
0#
#319
1.
1#
#320
0#
#321
0.
1#
#322
0#
#323
1.
1#
#324
0#
#325
0.
1#
#326
0#
#327
1.
1#
#328
0#
#329
0.
1#
#330
0#
#331
1.
1#
#332
0#
#333
0.
1#
#334
0#
#335
1.
1#
#336
0#
#337
0.
1#
#338
0#
#339
1.
1#
#340
0#
#341
0.
1#
#342
0#
#343
1.
1#
#344
0#
#345
0.
1#
#346
0#
#347
1.
1#
#348
0#
#349
0.
1#
#350
0#
#351
1.
1#
#352
0#
#353
0.
1#
#354
0#
#355
1.
1#
#356
0#
#357
0.
1#
#358
0#
#359
1.
1#
#360
0#
#361
0.
1#
#362
0#
#363
1.
1#
#364
0#
#365
0.
1#
#366
0#
#367
1.
1#
#368
0#
#369
0.
1#
#370
0#
#371
1.
1#
#372
0#
#373
0.
1#
#374
0#
#375
1.
1#
#376
0#
#377
0.
1#
#378
0#
#379
1.
1#
#380
0#
#381
0.
1#
#382
0#
#383
1.
1#
#384
0#
#385
0.
1#
#386
0#
#387
1.
1#
#388
0#
#389
0.
1#
#390
0#
#391
1.
1#
#392
0#
#393
0.
1#
#394
0#
#395
1.
1#
#396
0#
#397
0.
1#
#398
0#
#399
1.
1#
#400
0#
#401
0.
1#
#402
0#
#403
1.
1#
#404
0#
#405
0.
1#
#406
0#
#407
1.
1#
#408
0#
#409
0.
1#
#410
0#
#411
1.
1#
#412
0#
#413
0.
1#
#414
0#
#415
1.
1#
#416
0#
#417
0.
1#
#418
0#
#419
1.
1#
#420
0#
#421
0.
1#
#422
0#
#423
1.
1#
#424
0#
#425
0.
1#
#426
0#
#427
1.
1#
#428
0#
#429
0.
1#
#430
0#
#431
1.
1#
#432
0#
#433
0.
1#
#434
0#
#435
1.
1#
#436
0#
#437
0.
1#
#438
0#
#439
1.
1#
#440
0#
#441
0.
1#
#442
0#
#443
1.
1#
#444
0#
#445
0.
1#
#446
0#
#447
1.
1#
#448
0#
#449
0.
1#
#450
0#
#451
1.
1#
#452
0#
#453
0.
1#
#454
0#
#455
1.
1#
#456
0#
#457
0.
1#
#458
0#
#459
1.
1#
#460
0#
#461
0.
1#
#462
0#
#463
1.
1#
#464
0#
#465
0.
1#
#466
0#
#467
1.
1#
#468
0#
#469
0.
1#
#470
0#
#471
1.
1#
#472
0#
#473
0.
1#
#474
0#
#475
1.
1#
#476
0#
#477
0.
1#
#478
0#
#479
1.
1#
#480
0#
#481
0.
1#
#482
0#
#483
1.
1#
#484
0#
#485
0.
1#
#486
0#
#487
1.
1#
#488
0#
#489
0.
1#
#490
0#
#491
1.
1#
#492
0#
#493
0.
1#
#494
0#
#495
1.
1#
#496
0#
#497
0.
1#
#498
0#
#499
1.
1#
#500
0#
#501
0.
1#
#502
0#
#503
1.
1#
#504
0#
#505
0.
1#
#506
0#
#507
1.
1#
#508
0#
#509
0.
1#
#510
0#
#511
1.
1#
#512
0#
#513
0.
1#
#514
0#
#515
1.
1#
#516
0#
#517
0.
1#
#518
0#
#519
1.
1#
#520
0#
#521
0.
1#
#522
0#
#523
1.
1#
#524
0#
#525
0.
1#
#526
0#
#527
1.
1#
#528
0#
#529
0.
1#
#530
0#
#531
1.
1#
#532
0#
#533
0.
1#
#534
0#
#535
1.
1#
#536
0#
#537
0.
1#
#538
0#
#539
1.
1#
#540
0#
#541
0.
1#
#542
0#
#543
1.
1#
#544
0#
#545
0.
1#
#546
0#
#547
1.
1#
#548
0#
#549
0.
1#
#550
0#
#551
1.
1#
#552
0#
#553
0.
1#
#554
0#
#555
1.
1#
#556
0#
#557
0.
1#
#558
0#
#559
1.
1#
#560
0#
#561
0.
1#
#562
0#
#563
1.
1#
#564
0#
#565
0.
1#
#566
0#
#567
1.
1#
#568
0#
#569
0.
1#
#570
0#
#571
1.
1#
#572
0#
#573
0.
1#
#574
0#
#575
1.
1#
#576
0#
#577
0.
1#
#578
0#
#579
1.
1#
#580
0#
#581
0.
1#
#582
0#
#583
1.
1#
#584
0#
#585
0.
1#
#586
0#
#587
1.
1#
#588
0#
#589
0.
1#
#590
0#
#591
1.
1#
#592
0#
#593
0.
1#
#594
0#
#595
1.
1#
#596
0#
#597
0.
1#
#598
0#
#599
1.
1#
#600
0#
#601
0.
1#
#602
0#
#603
1.
1#
#604
0#
#605
0.
1#
#606
0#
#607
1.
1#
#608
0#
#609
0.
1#
#610
0#
#611
1.
1#
#612
0#
#613
0.
1#
#614
0#
#615
1.
1#
#616
0#
#617
0.
1#
#618
0#
#619
1.
1#
#620
0#
#621
0.
1#
#622
0#
#623
1.
1#
#624
0#
#625
0.
1#
#626
0#
#627
1.
1#
#628
0#
#629
0.
1#
#630
0#
#631
1.
1#
#632
0#
#633
0.
1#
#634
0#
#635
1.
1#
#636
0#
#637
0.
1#
#638
0#
#639
1.
1#
#640
0#
#641
0.
1#
#642
0#
#643
1.
1#
#644
0#
#645
0.
1#
#646
0#
#647
1.
1#
#648
0#
#649
0.
1#
#650
0#
#651
1.
1#
#652
0#
#653
0.
1#
#654
0#
#655
1.
1#
#656
0#
#657
0.
1#
#658
0#
#659
1.
1#
#660
0#
#661
0.
1#
#662
0#
#663
1.
1#
#664
0#
#665
0.
1#
#666
0#
#667
1.
1#
#668
0#
#669
0.
1#
#670
0#
#671
1.
1#
#672
0#
#673
0.
1#
#674
0#
#675
1.
1#
#676
0#
#677
0.
1#
#678
0#
#679
1.
1#
#680
0#
#681
0.
1#
#682
0#
#683
1.
1#
#684
0#
#685
0.
1#
#686
0#
#687
1.
1#
#688
0#
#689
0.
1#
#690
0#
#691
1.
1#
#692
0#
#693
0.
1#
#694
0#
#695
1.
1#
#696
0#
#697
0.
1#
#698
0#
#699
1.
1#
#700
0#
#701
0.
1#
#702
0#
#703
1.
1#
#704
0#
#705
0.
1#
#706
0#
#707
1.
1#
#708
0#
#709
0.
1#
#710
0#
#711
1.
1#
#712
0#
#713
0.
1#
#714
0#
#715
1.
1#
#716
0#
#717
0.
1#
#718
0#
#719
1.
1#
#720
0#
#721
0.
1#
#722
0#
#723
1.
1#
#724
0#
#725
0.
1#
#726
0#
#727
1.
1#
#728
0#
#729
0.
1#
#730
0#
#731
1.
1#
#732
0#
#733
0.
1#
#734
0#
#735
1.
1#
#736
0#
#737
0.
1#
#738
0#
#739
1.
1#
#740
0#
#741
0.
1#
#742
0#
#743
1.
1#
#744
0#
#745
0.
1#
#746
0#
#747
1.
1#
#748
0#
#749
0.
1#
#750
0#
#751
1.
1#
#752
0#
#753
0.
1#
#754
0#
#755
1.
1#
#756
0#
#757
0.
1#
#758
0#
#759
1.
1#
#760
0#
#761
0.
1#
#762
0#
#763
1.
1#
#764
0#
#765
0.
1#
#766
0#
#767
1.
1#
#768
0#
#769
0.
1#
#770
0#
#771
1.
1#
#772
0#
#773
0.
1#
#774
0#
#775
1.
1#
#776
0#
#777
0.
1#
#778
0#
#779
1.
1#
#780
0#
#781
0.
1#
#782
0#
#783
1.
1#
#784
0#
#785
0.
1#
#786
0#
#787
1.
1#
#788
0#
#789
0.
1#
#790
0#
#791
1.
1#
#792
0#
#793
0.
1#
#794
0#
#795
1.
1#
#796
0#
#797
0.
1#
#798
0#
#799
1.
1#
#800
0#
#801
0.
1#
#802
0#
#803
1.
1#
#804
0#
#805
0.
1#
#806
0#
#807
1.
1#
#808
0#
#809
0.
1#
#810
0#
#811
1.
1#
#812
0#
#813
0.
1#
#814
0#
#815
1.
1#
#816
0#
#817
0.
1#
#818
0#
#819
1.
1#
#820
0#
#821
0.
1#
#822
0#
#823
1.
1#
#824
0#
#825
0.
1#
#826
0#
#827
1.
1#
#828
0#
#829
0.
1#
#830
0#
#831
1.
1#
#832
0#
#833
0.
1#
#834
0#
#835
1.
1#
#836
0#
#837
0.
1#
#838
0#
#839
1.
1#
#840
0#
#841
0.
1#
#842
0#
#843
1.
1#
#844
0#
#845
0.
1#
#846
0#
#847
1.
1#
#848
0#
#849
0.
1#
#850
0#
#851
1.
1#
#852
0#
#853
0.
1#
#854
0#
#855
1.
1#
#856
0#
#857
0.
1#
#858
0#
#859
1.
1#
#860
0#
#861
0.
1#
#862
0#
#863
1.
1#
#864
0#
#865
0.
1#
#866
0#
#867
1.
1#
#868
0#
#869
0.
1#
#870
0#
#871
1.
1#
#872
0#
#873
0.
1#
#874
0#
#875
1.
1#
#876
0#
#877
0.
1#
#878
0#
#879
1.
1#
#880
0#
#881
0.
1#
#882
0#
#883
1.
1#
#884
0#
#885
0.
1#
#886
0#
#887
1.
1#
#888
0#
#889
0.
1#
#890
0#
#891
1.
1#
#892
0#
#893
0.
1#
#894
0#
#895
1.
1#
#896
0#
#897
0.
1#
#898
0#
#899
1.
1#
#900
0#
#901
0.
1#
#902
0#
#903
1.
1#
#904
0#
#905
0.
1#
#906
0#
#907
1.
1#
#908
0#
#909
0.
1#
#910
0#
#911
1.
1#
#912
0#
#913
0.
1#
#914
0#
#915
1.
1#
#916
0#
#917
0.
1#
#918
0#
#919
1.
1#
#920
0#
#921
0.
1#
#922
0#
#923
1.
1#
#924
0#
#925
0.
1#
#926
0#
#927
1.
1#
#928
0#
#929
0.
1#
#930
0#
#931
1.
1#
#932
0#
#933
0.
1#
#934
0#
#935
1.
1#
#936
0#
#937
0.
1#
#938
0#
#939
1.
1#
#940
0#
#941
0.
1#
#942
0#
#943
1.
1#
#944
0#
#945
0.
1#
#946
0#
#947
1.
1#
#948
0#
#949
0.
1#
#950
0#
#951
1.
1#
#952
0#
#953
0.
1#
#954
0#
#955
1.
1#
#956
0#
#957
0.
1#
#958
0#
#959
1.
1#
#960
0#
#961
0.
1#
#962
0#
#963
1.
1#
#964
0#
#965
0.
1#
#966
0#
#967
1.
1#
#968
0#
#969
0.
1#
#970
0#
#971
1.
1#
#972
0#
#973
0.
1#
#974
0#
#975
1.
1#
#976
0#
#977
0.
1#
#978
0#
#979
1.
1#
#980
0#
#981
0.
1#
#982
0#
#983
1.
1#
#984
0#
#985
0.
1#
#986
0#
#987
1.
1#
#988
0#
#989
0.
1#
#990
0#
#991
1.
1#
#992
0#
#993
0.
1#
#994
0#
#995
1.
1#
#996
0#
#997
0.
1#
#998
0#
#999
1.
1#
#1000
0#
#1001
0.
1#
#1002
0#
#1003
1.
1#
#1004
0#
#1005
0.
1#
#1006
0#
#1007
1.
1#
#1008
0#
#1009
0.
1#
#1010
0#
#1011
1.
1#
#1012
0#
#1013
0.
1#
#1014
0#
#1015
1.
1#
#1016
0#
#1017
0.
1#
#1018
0#
#1019
1.
1#
#1020
0#
#1021
0.
1#
#1022
0#
#1023
1.
1#
#1024
0#
#1025
0.
1#
#1026
0#
#1027
1.
1#
#1028
0#
#1029
0.
1#
#1030
0#
#1031
1.
1#
#1032
0#
#1033
0.
1#
#1034
0#
#1035
1.
1#
#1036
0#
#1037
0.
1#
#1038
0#
#1039
1.
1#
#1040
0#
#1041
0.
1#
#1042
0#
#1043
1.
1#
#1044
0#
#1045
0.
1#
#1046
0#
#1047
1.
1#
#1048
0#
#1049
0.
1#
#1050
0#
#1051
1.
1#
#1052
0#
#1053
0.
1#
#1054
0#
#1055
1.
1#
#1056
0#
#1057
0.
1#
#1058
0#
#1059
1.
1#
#1060
0#
#1061
0.
1#
#1062
0#
#1063
1.
1#
#1064
0#
#1065
0.
1#
#1066
0#
#1067
1.
1#
#1068
0#
#1069
0.
1#
#1070
0#
#1071
1.
1#
#1072
0#
#1073
0.
1#
#1074
0#
#1075
1.
1#
#1076
0#
#1077
0.
1#
#1078
0#
#1079
1.
1#
#1080
0#
#1081
0.
1#
#1082
0#
#1083
1.
1#
#1084
0#
#1085
0.
1#
#1086
0#
#1087
1.
1#
#1088
0#
#1089
0.
1#
#1090
0#
#1091
1.
1#
#1092
0#
#1093
0.
1#
#1094
0#
#1095
1.
1#
#1096
0#
#1097
0.
1#
#1098
0#
#1099
1.
1#
#1100
0#
#1101
0.
1#
#1102
0#
#1103
1.
1#
#1104
0#
#1105
0.
1#
#1106
0#
#1107
1.
1#
#1108
0#
#1109
0.
1#
#1110
0#
#1111
1.
1#
#1112
0#
#1113
0.
1#
#1114
0#
#1115
1.
1#
#1116
0#
#1117
0.
1#
#1118
0#
#1119
1.
1#
#1120
0#
#1121
0.
1#
#1122
0#
#1123
1.
1#
#1124
0#
#1125
0.
1#
#1126
0#
#1127
1.
1#
#1128
0#
#1129
0.
1#
#1130
0#
#1131
1.
1#
#1132
0#
#1133
0.
1#
#1134
0#
#1135
1.
1#
#1136
0#
#1137
0.
1#
#1138
0#
#1139
1.
1#
#1140
0#
#1141
0.
1#
#1142
0#
#1143
1.
1#
#1144
0#
#1145
0.
1#
#1146
0#
#1147
1.
1#
#1148
0#
#1149
0.
1#
#1150
0#
#1151
1.
1#
#1152
0#
#1153
0.
1#
#1154
0#
#1155
1.
1#
#1156
0#
#1157
0.
1#
#1158
0#
#1159
1.
1#
#1160
0#
#1161
0.
1#
#1162
0#
#1163
1.
1#
#1164
0#
#1165
0.
1#
#1166
0#
#1167
1.
1#
#1168
0#
#1169
0.
1#
#1170
0#
#1171
1.
1#
#1172
0#
#1173
0.
1#
#1174
0#
#1175
1.
1#
#1176
0#
#1177
0.
1#
#1178
0#
#1179
1.
1#
#1180
0#
#1181
0.
1#
#1182
0#
#1183
1.
1#
#1184
0#
#1185
0.
1#
#1186
0#
#1187
1.
1#
#1188
0#
#1189
0.
1#
#1190
0#
#1191
1.
1#
#1192
0#
#1193
0.
1#
#1194
0#
#1195
1.
1#
#1196
0#
#1197
0.
1#
#1198
0#
#1199
1.
1#
#1200
0#
#1201
0.
1#
#1202
0#
#1203
1.
1#
#1204
0#
#1205
0.
1#
#1206
0#
#1207
1.
1#
#1208
0#
#1209
0.
1#
#1210
0#
#1211
1.
1#
#1212
0#
#1213
0.
1#
#1214
0#
#1215
1.
1#
#1216
0#
#1217
0.
1#
#1218
0#
#1219
1.
1#
#1220
0#
#1221
0.
1#
#1222
0#
#1223
1.
1#
#1224
0#
#1225
0.
1#
#1226
0#
#1227
1.
1#
#1228
0#
#1229
0.
1#
#1230
0#
#1231
1.
1#
#1232
0#
#1233
0.
1#
#1234
0#
#1235
1.
1#
#1236
0#
#1237
0.
1#
#1238
0#
#1239
1.
1#
#1240
0#
#1241
0.
1#
#1242
0#
#1243
1.
1#
#1244
0#
#1245
0.
1#
#1246
0#
#1247
1.
1#
#1248
0#
#1249
0.
1#
#1250
0#
#1251
1.
1#
#1252
0#
#1253
0.
1#
#1254
0#
#1255
1.
1#
#1256
0#
#1257
0.
1#
#1258
0#
#1259
1.
1#
#1260
0#
#1261
0.
1#
#1262
0#
#1263
1.
1#
#1264
0#
#1265
0.
1#
#1266
0#
#1267
1.
1#
#1268
0#
#1269
0.
1#
#1270
0#
#1271
1.
1#
#1272
0#
#1273
0.
1#
#1274
0#
#1275
1.
1#
#1276
0#
#1277
0.
1#
#1278
0#
#1279
1.
1#
#1280
0#
#1281
0.
1#
#1282
0#
#1283
1.
1#
#1284
0#
#1285
0.
1#
#1286
0#
#1287
1.
1#
#1288
0#
#1289
0.
1#
#1290
0#
#1291
1.
1#
#1292
0#
#1293
0.
1#
#1294
0#
#1295
1.
1#
#1296
0#
#1297
0.
1#
#1298
0#
#1299
1.
1#
#1300
0#
#1301
0.
1#
#1302
0#
#1303
1.
1#
#1304
0#
#1305
0.
1#
#1306
0#
#1307
1.
1#
#1308
0#
#1309
0.
1#
#1310
0#
#1311
1.
1#
#1312
0#
#1313
0.
1#
#1314
0#
#1315
1.
1#
#1316
0#
#1317
0.
1#
#1318
0#
#1319
1.
1#
#1320
0#
#1321
0.
1#
#1322
0#
#1323
1.
1#
#1324
0#
#1325
0.
1#
#1326
0#
#1327
1.
1#
#1328
0#
#1329
0.
1#
#1330
0#
#1331
1.
1#
#1332
0#
#1333
0.
1#
#1334
0#
#1335
1.
1#
#1336
0#
#1337
0.
1#
#1338
0#
#1339
1.
1#
#1340
0#
#1341
0.
1#
#1342
0#
#1343
1.
1#
#1344
0#
#1345
0.
1#
#1346
0#
#1347
1.
1#
#1348
0#
#1349
0.
1#
#1350
0#
#1351
1.
1#
#1352
0#
#1353
0.
1#
#1354
0#
#1355
1.
1#
#1356
0#
#1357
0.
1#
#1358
0#
#1359
1.
1#
#1360
0#
#1361
0.
1#
#1362
0#
#1363
1.
1#
#1364
0#
#1365
0.
1#
#1366
0#
#1367
1.
1#
#1368
0#
#1369
0.
1#
#1370
0#
#1371
1.
1#
#1372
0#
#1373
0.
1#
#1374
0#
#1375
1.
1#
#1376
0#
#1377
0.
1#
#1378
0#
#1379
1.
1#
#1380
0#
#1381
0.
1#
#1382
0#
#1383
1.
1#
#1384
0#
#1385
0.
1#
#1386
0#
#1387
1.
1#
#1388
0#
#1389
0.
1#
#1390
0#
#1391
1.
1#
#1392
0#
#1393
0.
1#
#1394
0#
#1395
1.
1#
#1396
0#
#1397
0.
1#
#1398
0#
#1399
1.
1#
#1400
0#
#1401
0.
1#
#1402
0#
#1403
1.
1#
#1404
0#
#1405
0.
1#
#1406
0#
#1407
1.
1#
#1408
0#
#1409
0.
1#
#1410
0#
#1411
1.
1#
#1412
0#
#1413
0.
1#
#1414
0#
#1415
1.
1#
#1416
0#
#1417
0.
1#
#1418
0#
#1419
1.
1#
#1420
0#
#1421
0.
1#
#1422
0#
#1423
1.
1#
#1424
0#
#1425
0.
1#
#1426
0#
#1427
1.
1#
#1428
0#
#1429
0.
1#
#1430
0#
#1431
1.
1#
#1432
0#
#1433
0.
1#
#1434
0#
#1435
1.
1#
#1436
0#
#1437
0.
1#
#1438
0#
#1439
1.
1#
#1440
0#
#1441
0.
1#
#1442
0#
#1443
1.
1#
#1444
0#
#1445
0.
1#
#1446
0#
#1447
1.
1#
#1448
0#
#1449
0.
1#
#1450
0#
#1451
1.
1#
#1452
0#
#1453
0.
1#
#1454
0#
#1455
1.
1#
#1456
0#
#1457
0.
1#
#1458
0#
#1459
1.
1#
#1460
0#
#1461
0.
1#
#1462
0#
#1463
1.
1#
#1464
0#
#1465
0.
1#
#1466
0#
#1467
1.
1#
#1468
0#
#1469
0.
1#
#1470
0#
#1471
1.
1#
#1472
0#
#1473
0.
1#
#1474
0#
#1475
1.
1#
#1476
0#
#1477
0.
1#
#1478
0#
#1479
1.
1#
#1480
0#
#1481
0.
1#
#1482
0#
#1483
1.
1#
#1484
0#
#1485
0.
1#
#1486
0#
#1487
1.
1#
#1488
0#
#1489
0.
1#
#1490
0#
#1491
1.
1#
#1492
0#
#1493
0.
1#
#1494
0#
#1495
1.
1#
#1496
0#
#1497
0.
1#
#1498
0#
#1499
1.
1#
#1500
0#
#1501
0.
1#
#1502
0#
#1503
1.
1#
#1504
0#
#1505
0.
1#
#1506
0#
#1507
1.
1#
#1508
0#
#1509
0.
1#
#1510
0#
#1511
1.
1#
