test07/serial_s.v
/*
 Produced by NSL Core(version=20151214), IP ARCH, Inc. Sat Apr  9 14:56:31 2016
 Licensed to :EVALUATION USER
*/
/*
 DO NOT USE ANY PART OF THIS FILE FOR COMMERCIAL PRODUCTS. 
*/

module counter ( p_reset , m_clock , f , countup , reset );
  input p_reset, m_clock;
  wire p_reset, m_clock;
  output [12:0] f;
  wire [12:0] f;
  input countup;
  wire countup;
  input reset;
  wire reset;
  reg [12:0] cnt;
  wire _net_0;
  wire _net_1;

   assign  _net_0 = 
// synthesis translate_off
// synopsys translate_off
(countup)? 
// synthesis translate_on
// synopsys translate_on
((countup)?(cnt != 13'b1010001010000):1'b0)
// synthesis translate_off
// synopsys translate_off
:1'bx
// synthesis translate_on
// synopsys translate_on
;
   assign  _net_1 = 
// synthesis translate_off
// synopsys translate_off
(countup)? 
// synthesis translate_on
// synopsys translate_on
((countup)?(cnt==13'b1010001010000):1'b0)
// synthesis translate_off
// synopsys translate_off
:1'bx
// synthesis translate_on
// synopsys translate_on
;
   assign  f = cnt;
always @(posedge m_clock or posedge p_reset)
  begin
if (p_reset)
     cnt <= 13'b0000000000000;
else 
// synthesis translate_off
// synopsys translate_off
if ((((countup&_net_1)&(countup&_net_0))|(((countup&_net_1)|(countup&_net_0))&reset)))   cnt <= 13'bx; 
  else 
// synthesis translate_on
// synopsys translate_on
if ((countup&_net_1))
      cnt <= 13'b0000000000000;
else if ((countup&_net_0))
      cnt <= (cnt+13'b0000000000001);
else if (reset)
      cnt <= 13'b0000000000000;
end

// synthesis translate_off
// synopsys translate_off
always @(posedge m_clock)
  begin
if (((((countup&_net_1)|(countup&_net_0))|reset)==1'b1) ||
 ((((countup&_net_1)|(countup&_net_0))|reset)==1'b0) ) begin
 if ((((countup&_net_1)&(countup&_net_0))|(((countup&_net_1)|(countup&_net_0))&reset)))
 begin $display("Warning: assign collision(counter:cnt) at %d",$time);

  end
 end
 else 
 $display("Warning: register set hazard(counter:cnt) at %d",$time);

  end

// synthesis translate_on
// synopsys translate_on
endmodule
/*
 Produced by NSL Core(version=20151214), IP ARCH, Inc. Sat Apr  9 14:56:31 2016
 Licensed to :EVALUATION USER
*/
/*
 Produced by NSL Core(version=20151214), IP ARCH, Inc. Sat Apr  9 14:56:31 2016
 Licensed to :EVALUATION USER
*/
/*
 DO NOT USE ANY PART OF THIS FILE FOR COMMERCIAL PRODUCTS. 
*/

module serial_s ( p_reset , m_clock , start_send , TDX );
  input p_reset, m_clock;
  wire p_reset, m_clock;
  input start_send;
  wire start_send;
  output TDX;
  wire TDX;
  reg TDX_r;
  reg sending;
  reg [7:0] data;
  reg [3:0] loop;
  wire send;
  wire [3:0] _net_6;
  wire [12:0] _counter_i_f;
  wire _counter_i_countup;
  wire _counter_i_reset;
  wire _counter_i_p_reset;
  wire _counter_i_m_clock;
  wire _net_9;
  wire _net_10;
  reg _reg_11;
  reg _reg_12;
  reg _reg_13;
  reg _reg_14;
  reg _reg_15;
  reg _reg_16;
  reg _reg_17;
  reg _reg_18;
  reg _reg_19;
  reg _reg_20;
  reg _reg_21;
  wire _net_22;
  wire _reg_13_goto;
  wire _reg_12_goin;
  wire _net_23;
  wire _reg_13_goin;
  wire _net_25;
  wire _reg_15_goto;
  wire _reg_17_goin;
  wire _net_26;
  wire _reg_16_goto;
  wire _reg_15_goin;
  wire _net_27;
  wire _reg_16_goin;
  wire _net_28;
  wire _reg_17_goto;
  wire _reg_14_goin;
counter counter_i (.m_clock(m_clock), .p_reset(p_reset), .reset(_counter_i_reset), .countup(_counter_i_countup), .f(_counter_i_f));


// synthesis translate_off
// synopsys translate_off
always @(posedge send)
  begin
#1 if (send===1'bx)
 begin
$display("Warning: control hazard(serial_s:send) at %d",$time);
 end
#1 if ((((_net_9&_net_10))===1'bx) || (1'b1)===1'bx) $display("hazard ((_net_9&_net_10) || 1'b1) line 46 at %d\n",$time);
 end

// synthesis translate_on
// synopsys translate_on
   assign  send = (_net_9&_net_10);
   assign  _net_6 = 
// synthesis translate_off
// synopsys translate_off
(_reg_15)? 
// synthesis translate_on
// synopsys translate_on
((_reg_15)?(loop+4'b0001):4'b0)
// synthesis translate_off
// synopsys translate_off
:4'bx
// synthesis translate_on
// synopsys translate_on
;

// synthesis translate_off
// synopsys translate_off
always @(posedge _counter_i_countup)
  begin
#1 if (_counter_i_countup===1'bx)
 begin
$display("Warning: control hazard(serial_s:_counter_i_countup) at %d",$time);
 end
#1 if ((((_reg_16&(~_net_26)))===1'bx) || (1'b1)===1'bx) $display("hazard ((_reg_16&(~_net_26)) || 1'b1) line 60 at %d\n",$time);
#1 if ((((_reg_13&(~_net_22)))===1'bx) || (1'b1)===1'bx) $display("hazard ((_reg_13&(~_net_22)) || 1'b1) line 66 at %d\n",$time);
 end

// synthesis translate_on
// synopsys translate_on
   assign  _counter_i_countup = (_reg_16&(~_net_26))|
    (_reg_13&(~_net_22));

// synthesis translate_off
// synopsys translate_off
always @(posedge _counter_i_reset)
  begin
#1 if (_counter_i_reset===1'bx)
 begin
$display("Warning: control hazard(serial_s:_counter_i_reset) at %d",$time);
 end
#1 if (((_reg_20)===1'bx) || (1'b1)===1'bx) $display("hazard (_reg_20 || 1'b1) line 52 at %d\n",$time);
#1 if ((((_reg_17&(~_net_28)))===1'bx) || (1'b1)===1'bx) $display("hazard ((_reg_17&(~_net_28)) || 1'b1) line 58 at %d\n",$time);
 end

// synthesis translate_on
// synopsys translate_on
   assign  _counter_i_reset = _reg_20|
    (_reg_17&(~_net_28));
   assign  _counter_i_p_reset = p_reset;
   assign  _counter_i_m_clock = m_clock;
   assign  _net_9 = (start_send==1'b1);
   assign  _net_10 = 
// synthesis translate_off
// synopsys translate_off
(_net_9)? 
// synthesis translate_on
// synopsys translate_on
((_net_9)?(sending==1'b0):1'b0)
// synthesis translate_off
// synopsys translate_off
:1'bx
// synthesis translate_on
// synopsys translate_on
;
   assign  _net_22 = 
// synthesis translate_off
// synopsys translate_off
(_reg_13)? 
// synthesis translate_on
// synopsys translate_on
((_reg_13)?(~(_counter_i_f != 13'b1010001010000)):1'b0)
// synthesis translate_off
// synopsys translate_off
:1'bx
// synthesis translate_on
// synopsys translate_on
;

// synthesis translate_off
// synopsys translate_off
always @(posedge _reg_13_goto)
  begin
#1 if (_reg_13_goto===1'bx)
 begin
$display("Warning: control hazard(serial_s:_reg_13_goto) at %d",$time);
 end
#1 if (((((_reg_13&(~_net_22))&_net_23))===1'bx) || (1'b1)===1'bx) $display("hazard (((_reg_13&(~_net_22))&_net_23) || 1'b1) line 67 at %d\n",$time);
#1 if ((((_reg_13&_net_22))===1'bx) || (1'b1)===1'bx) $display("hazard ((_reg_13&_net_22) || 1'b1) line 67 at %d\n",$time);
 end

// synthesis translate_on
// synopsys translate_on
   assign  _reg_13_goto = ((_reg_13&(~_net_22))&_net_23)|
    (_reg_13&_net_22);

// synthesis translate_off
// synopsys translate_off
always @(posedge _reg_12_goin)
  begin
#1 if (_reg_12_goin===1'bx)
 begin
$display("Warning: control hazard(serial_s:_reg_12_goin) at %d",$time);
 end
#1 if ((((_reg_13&_net_22))===1'bx) || (1'b1)===1'bx) $display("hazard ((_reg_13&_net_22) || 1'b1) line 67 at %d\n",$time);
 end

// synthesis translate_on
// synopsys translate_on
   assign  _reg_12_goin = (_reg_13&_net_22);
   assign  _net_23 = 
// synthesis translate_off
// synopsys translate_off
((_reg_13&(~_net_22)))? 
// synthesis translate_on
// synopsys translate_on
(((_reg_13&(~_net_22)))?(_counter_i_f != 13'b1010001010000):1'b0)
// synthesis translate_off
// synopsys translate_off
:1'bx
// synthesis translate_on
// synopsys translate_on
;

// synthesis translate_off
// synopsys translate_off
always @(posedge _reg_13_goin)
  begin
#1 if (_reg_13_goin===1'bx)
 begin
$display("Warning: control hazard(serial_s:_reg_13_goin) at %d",$time);
 end
#1 if (((((_reg_13&(~_net_22))&_net_23))===1'bx) || (1'b1)===1'bx) $display("hazard (((_reg_13&(~_net_22))&_net_23) || 1'b1) line 67 at %d\n",$time);
 end

// synthesis translate_on
// synopsys translate_on
   assign  _reg_13_goin = ((_reg_13&(~_net_22))&_net_23);

// synthesis translate_off
// synopsys translate_off
always @(posedge m_clock)
  begin
    if(_reg_14)
    begin
    $display("sending finish bit");
    end
  end

// synthesis translate_on
// synopsys translate_on
   assign  _net_25 = 
// synthesis translate_off
// synopsys translate_off
(_reg_15)? 
// synthesis translate_on
// synopsys translate_on
((_reg_15)?(_net_6 < 4'b1000):1'b0)
// synthesis translate_off
// synopsys translate_off
:1'bx
// synthesis translate_on
// synopsys translate_on
;

// synthesis translate_off
// synopsys translate_off
always @(posedge _reg_15_goto)
  begin
#1 if (_reg_15_goto===1'bx)
 begin
$display("Warning: control hazard(serial_s:_reg_15_goto) at %d",$time);
 end
#1 if ((((_reg_15&_net_25))===1'bx) || (1'b1)===1'bx) $display("hazard ((_reg_15&_net_25) || 1'b1) line 63 at %d\n",$time);
 end

// synthesis translate_on
// synopsys translate_on
   assign  _reg_15_goto = (_reg_15&_net_25);

// synthesis translate_off
// synopsys translate_off
always @(posedge _reg_17_goin)
  begin
#1 if (_reg_17_goin===1'bx)
 begin
$display("Warning: control hazard(serial_s:_reg_17_goin) at %d",$time);
 end
#1 if ((((_reg_15&_net_25))===1'bx) || (1'b1)===1'bx) $display("hazard ((_reg_15&_net_25) || 1'b1) line 63 at %d\n",$time);
 end

// synthesis translate_on
// synopsys translate_on
   assign  _reg_17_goin = (_reg_15&_net_25);
   assign  _net_26 = 
// synthesis translate_off
// synopsys translate_off
(_reg_16)? 
// synthesis translate_on
// synopsys translate_on
((_reg_16)?(~(_counter_i_f != 13'b1010001010000)):1'b0)
// synthesis translate_off
// synopsys translate_off
:1'bx
// synthesis translate_on
// synopsys translate_on
;

// synthesis translate_off
// synopsys translate_off
always @(posedge _reg_16_goto)
  begin
#1 if (_reg_16_goto===1'bx)
 begin
$display("Warning: control hazard(serial_s:_reg_16_goto) at %d",$time);
 end
#1 if (((((_reg_16&(~_net_26))&_net_27))===1'bx) || (1'b1)===1'bx) $display("hazard (((_reg_16&(~_net_26))&_net_27) || 1'b1) line 61 at %d\n",$time);
#1 if ((((_reg_16&_net_26))===1'bx) || (1'b1)===1'bx) $display("hazard ((_reg_16&_net_26) || 1'b1) line 61 at %d\n",$time);
 end

// synthesis translate_on
// synopsys translate_on
   assign  _reg_16_goto = ((_reg_16&(~_net_26))&_net_27)|
    (_reg_16&_net_26);

// synthesis translate_off
// synopsys translate_off
always @(posedge _reg_15_goin)
  begin
#1 if (_reg_15_goin===1'bx)
 begin
$display("Warning: control hazard(serial_s:_reg_15_goin) at %d",$time);
 end
#1 if ((((_reg_16&_net_26))===1'bx) || (1'b1)===1'bx) $display("hazard ((_reg_16&_net_26) || 1'b1) line 61 at %d\n",$time);
 end

// synthesis translate_on
// synopsys translate_on
   assign  _reg_15_goin = (_reg_16&_net_26);
   assign  _net_27 = 
// synthesis translate_off
// synopsys translate_off
((_reg_16&(~_net_26)))? 
// synthesis translate_on
// synopsys translate_on
(((_reg_16&(~_net_26)))?(_counter_i_f != 13'b1010001010000):1'b0)
// synthesis translate_off
// synopsys translate_off
:1'bx
// synthesis translate_on
// synopsys translate_on
;

// synthesis translate_off
// synopsys translate_off
always @(posedge _reg_16_goin)
  begin
#1 if (_reg_16_goin===1'bx)
 begin
$display("Warning: control hazard(serial_s:_reg_16_goin) at %d",$time);
 end
#1 if (((((_reg_16&(~_net_26))&_net_27))===1'bx) || (1'b1)===1'bx) $display("hazard (((_reg_16&(~_net_26))&_net_27) || 1'b1) line 61 at %d\n",$time);
 end

// synthesis translate_on
// synopsys translate_on
   assign  _reg_16_goin = ((_reg_16&(~_net_26))&_net_27);
   assign  _net_28 = 
// synthesis translate_off
// synopsys translate_off
(_reg_17)? 
// synthesis translate_on
// synopsys translate_on
((_reg_17)?(~(loop < 4'b1000)):1'b0)
// synthesis translate_off
// synopsys translate_off
:1'bx
// synthesis translate_on
// synopsys translate_on
;

// synthesis translate_off
// synopsys translate_off
always @(posedge _reg_17_goto)
  begin
#1 if (_reg_17_goto===1'bx)
 begin
$display("Warning: control hazard(serial_s:_reg_17_goto) at %d",$time);
 end
#1 if ((((_reg_17&_net_28))===1'bx) || (1'b1)===1'bx) $display("hazard ((_reg_17&_net_28) || 1'b1) line 63 at %d\n",$time);
 end

// synthesis translate_on
// synopsys translate_on
   assign  _reg_17_goto = (_reg_17&_net_28);

// synthesis translate_off
// synopsys translate_off
always @(posedge _reg_14_goin)
  begin
#1 if (_reg_14_goin===1'bx)
 begin
$display("Warning: control hazard(serial_s:_reg_14_goin) at %d",$time);
 end
#1 if ((((_reg_17&_net_28))===1'bx) || (1'b1)===1'bx) $display("hazard ((_reg_17&_net_28) || 1'b1) line 63 at %d\n",$time);
 end

// synthesis translate_on
// synopsys translate_on
   assign  _reg_14_goin = (_reg_17&_net_28);

// synthesis translate_off
// synopsys translate_off
always @(posedge m_clock)
  begin
    if((send|_reg_21))
    begin
    $display("Sending...");
    end
  end

// synthesis translate_on
// synopsys translate_on
   assign  TDX = TDX_r;
always @(posedge m_clock or posedge p_reset)
  begin
if (p_reset)
     TDX_r <= 1'b1;
else 
// synthesis translate_off
// synopsys translate_off
if (((_reg_19&_reg_15)|((_reg_19|_reg_15)&_reg_12)))   TDX_r <= 1'bx; 
  else 
// synthesis translate_on
// synopsys translate_on
if (_reg_19)
      TDX_r <= 1'b0;
else if (_reg_15)
      TDX_r <= (data[loop]);
else if (_reg_12)
      TDX_r <= 1'b1;
end

// synthesis translate_off
// synopsys translate_off
always @(posedge m_clock)
  begin
if ((((_reg_19|_reg_15)|_reg_12)==1'b1) ||
 (((_reg_19|_reg_15)|_reg_12)==1'b0) ) begin
 if (((_reg_19&_reg_15)|((_reg_19|_reg_15)&_reg_12)))
 begin $display("Warning: assign collision(serial_s:TDX_r) at %d",$time);

  end
 end
 else 
 $display("Warning: register set hazard(serial_s:TDX_r) at %d",$time);

  end

// synthesis translate_on
// synopsys translate_on
always @(posedge m_clock or posedge p_reset)
  begin
if (p_reset)
     sending <= 1'b0;
else 
// synthesis translate_off
// synopsys translate_off
if ((_reg_11&(_net_9&_net_10)))   sending <= 1'bx; 
  else 
// synthesis translate_on
// synopsys translate_on
if (_reg_11)
      sending <= 1'b0;
else if ((_net_9&_net_10))
      sending <= 1'b1;
end

// synthesis translate_off
// synopsys translate_off
always @(posedge m_clock)
  begin
if (((_reg_11|(_net_9&_net_10))==1'b1) ||
 ((_reg_11|(_net_9&_net_10))==1'b0) ) begin
 if ((_reg_11&(_net_9&_net_10)))
 begin $display("Warning: assign collision(serial_s:sending) at %d",$time);

  end
 end
 else 
 $display("Warning: register set hazard(serial_s:sending) at %d",$time);

  end

// synthesis translate_on
// synopsys translate_on
always @(posedge m_clock)
  begin
if ((_net_9&_net_10))
      data <= 8'b00110100;
end
always @(posedge m_clock or posedge p_reset)
  begin
if (p_reset)
     loop <= 4'b0000;
else 
// synthesis translate_off
// synopsys translate_off
if ((_reg_18&_reg_15))   loop <= 4'bx; 
  else 
// synthesis translate_on
// synopsys translate_on
if (_reg_18)
      loop <= 4'b0000;
else if (_reg_15)
      loop <= _net_6;
end

// synthesis translate_off
// synopsys translate_off
always @(posedge m_clock)
  begin
if (((_reg_18|_reg_15)==1'b1) ||
 ((_reg_18|_reg_15)==1'b0) ) begin
 if ((_reg_18&_reg_15))
 begin $display("Warning: assign collision(serial_s:loop) at %d",$time);

  end
 end
 else 
 $display("Warning: register set hazard(serial_s:loop) at %d",$time);

  end

// synthesis translate_on
// synopsys translate_on
always @(posedge m_clock or posedge p_reset)
  begin
if (p_reset)
     _reg_11 <= 1'b0;
else if ((_reg_11|_reg_12))
      _reg_11 <= _reg_12;
end
always @(posedge m_clock or posedge p_reset)
  begin
if (p_reset)
     _reg_12 <= 1'b0;
else if (((_reg_13&_net_22)|(_reg_12|_reg_13)))
      _reg_12 <= ((_reg_13&_net_22)|(_reg_13&(~_reg_13_goto)));
end
always @(posedge m_clock or posedge p_reset)
  begin
if (p_reset)
     _reg_13 <= 1'b0;
else if ((((_reg_13&(~_net_22))&_net_23)|(_reg_13|_reg_14)))
      _reg_13 <= (((_reg_13&(~_net_22))&_net_23)|_reg_14);
end
always @(posedge m_clock or posedge p_reset)
  begin
if (p_reset)
     _reg_14 <= 1'b0;
else if (((_reg_17&_net_28)|(_reg_14|_reg_15)))
      _reg_14 <= ((_reg_17&_net_28)|(_reg_15&(~_reg_15_goto)));
end
always @(posedge m_clock or posedge p_reset)
  begin
if (p_reset)
     _reg_15 <= 1'b0;
else if (((_reg_16&_net_26)|(_reg_15|_reg_16)))
      _reg_15 <= ((_reg_16&_net_26)|(_reg_16&(~_reg_16_goto)));
end
always @(posedge m_clock or posedge p_reset)
  begin
if (p_reset)
     _reg_16 <= 1'b0;
else if ((((_reg_16&(~_net_26))&_net_27)|(_reg_16|_reg_17)))
      _reg_16 <= (((_reg_16&(~_net_26))&_net_27)|(_reg_17&(~_reg_17_goto)));
end
always @(posedge m_clock or posedge p_reset)
  begin
if (p_reset)
     _reg_17 <= 1'b0;
else if (((_reg_15&_net_25)|(_reg_17|_reg_18)))
      _reg_17 <= ((_reg_15&_net_25)|_reg_18);
end
always @(posedge m_clock or posedge p_reset)
  begin
if (p_reset)
     _reg_18 <= 1'b0;
else if ((_reg_18|_reg_19))
      _reg_18 <= _reg_19;
end
always @(posedge m_clock or posedge p_reset)
  begin
if (p_reset)
     _reg_19 <= 1'b0;
else if ((_reg_19|_reg_20))
      _reg_19 <= _reg_20;
end
always @(posedge m_clock or posedge p_reset)
  begin
if (p_reset)
     _reg_20 <= 1'b0;
else if ((send|(_reg_20|_reg_21)))
      _reg_20 <= (_reg_21|send);
end
always @(posedge m_clock or posedge p_reset)
  begin
if (p_reset)
     _reg_21 <= 1'b0;
else if (_reg_21)
      _reg_21 <= 1'b0;
end
endmodule
/*
 Produced by NSL Core(version=20151214), IP ARCH, Inc. Sat Apr  9 14:56:31 2016
 Licensed to :EVALUATION USER
*/

test07_max10/testbench.v
`timescale 1ns/1ns

module testbench;
  reg p_reset, m_clock, start_send;
  wire TDX;

  initial begin
    $dumpfile("testbench.vcd");
    $dumpvars(0, testbench);
    m_clock = 0;
    start_send = 0;
    p_reset = 1;
    #100
    p_reset = 0;
    #100
    #100
    start_send = 1;
    #20
    start_send = 0;
    #1000000
    $finish;
  end

  always #10 begin
    m_clock = ~m_clock;
  end
  serial_s serial_s (
    .p_reset(p_reset),
    .m_clock(m_clock),
    .start_send(start_send),
    .TDX(TDX)
  );
endmodule

test07/testbench.vcd
$date
	Sat Apr  9 14:57:03 2016
$end
$version
	Icarus Verilog
$end
$timescale
	1ns
$end
$scope module testbench $end
$var wire 1 ! TDX $end
$var reg 1 " m_clock $end
$var reg 1 # p_reset $end
$var reg 1 $ start_send $end
$scope module serial_s $end
$var wire 1 ! TDX $end
$var wire 1 % _counter_i_countup $end
$var wire 1 & _counter_i_m_clock $end
$var wire 1 ' _counter_i_p_reset $end
$var wire 1 ( _counter_i_reset $end
$var wire 1 ) _net_9 $end
$var wire 1 * _reg_12_goin $end
$var wire 1 + _reg_13_goin $end
$var wire 1 , _reg_13_goto $end
$var wire 1 - _reg_14_goin $end
$var wire 1 . _reg_15_goin $end
$var wire 1 / _reg_15_goto $end
$var wire 1 0 _reg_16_goin $end
$var wire 1 1 _reg_16_goto $end
$var wire 1 2 _reg_17_goin $end
$var wire 1 3 _reg_17_goto $end
$var wire 1 " m_clock $end
$var wire 1 # p_reset $end
$var wire 1 4 send $end
$var wire 1 $ start_send $end
$var wire 4 5 _net_6 [3:0] $end
$var wire 1 6 _net_28 $end
$var wire 1 7 _net_27 $end
$var wire 1 8 _net_26 $end
$var wire 1 9 _net_25 $end
$var wire 1 : _net_23 $end
$var wire 1 ; _net_22 $end
$var wire 1 < _net_10 $end
$var wire 13 = _counter_i_f [12:0] $end
$var reg 1 > TDX_r $end
$var reg 1 ? _reg_11 $end
$var reg 1 @ _reg_12 $end
$var reg 1 A _reg_13 $end
$var reg 1 B _reg_14 $end
$var reg 1 C _reg_15 $end
$var reg 1 D _reg_16 $end
$var reg 1 E _reg_17 $end
$var reg 1 F _reg_18 $end
$var reg 1 G _reg_19 $end
$var reg 1 H _reg_20 $end
$var reg 1 I _reg_21 $end
$var reg 8 J data [7:0] $end
$var reg 4 K loop [3:0] $end
$var reg 1 L sending $end
$scope module counter_i $end
$var wire 1 % countup $end
$var wire 13 M f [12:0] $end
$var wire 1 " m_clock $end
$var wire 1 # p_reset $end
$var wire 1 ( reset $end
$var wire 1 N _net_1 $end
$var wire 1 O _net_0 $end
$var reg 13 P cnt [12:0] $end
$upscope $end
$upscope $end
$upscope $end
$enddefinitions $end
#0
$dumpvars
b0 P
xO
xN
b0 M
0L
b0 K
bx J
0I
0H
0G
0F
0E
0D
0C
0B
0A
0@
0?
1>
b0 =
x<
x;
x:
x9
x8
x7
x6
bx 5
04
03
02
01
00
0/
0.
0-
0,
0+
0*
0)
0(
1'
0&
0%
0$
1#
0"
1!
$end
#10
1&
1"
#20
0&
0"
#30
1&
1"
#40
0&
0"
#50
1&
1"
#60
0&
0"
#70
1&
1"
#80
0&
0"
#90
1&
1"
#100
0&
0"
0'
0#
#110
1&
1"
#120
0&
0"
#130
1&
1"
#140
0&
0"
#150
1&
1"
#160
0&
0"
#170
1&
1"
#180
0&
0"
#190
1&
1"
#200
0&
0"
#210
1&
1"
#220
0&
0"
#230
1&
1"
#240
0&
0"
#250
1&
1"
#260
0&
0"
#270
1&
1"
#280
0&
0"
#290
1&
1"
#300
1<
14
1)
0&
0"
1$
#310
04
0<
1(
b110100 J
1L
1H
1&
1"
#320
x<
0)
0&
0"
0$
#330
0(
0H
1G
1&
1"
#340
0&
0"
#350
0!
0>
1F
0G
1&
1"
#360
0&
0"
#370
1(
06
0-
03
0F
1E
1&
1"
#380
0&
0"
#390
1O
17
0N
10
11
1%
0(
08
0.
x6
1D
0E
1&
1"
#400
0&
0"
#410
b1 =
b1 M
b1 P
1&
1"
#420
0&
0"
#430
b10 =
b10 M
b10 P
1&
1"
#440
0&
0"
#450
b11 =
b11 M
b11 P
1&
1"
#460
0&
0"
#470
b100 =
b100 M
b100 P
1&
1"
#480
0&
0"
#490
b101 =
b101 M
b101 P
1&
1"
#500
0&
0"
#510
b110 =
b110 M
b110 P
1&
1"
#520
0&
0"
#530
b111 =
b111 M
b111 P
1&
1"
#540
0&
0"
#550
b1000 =
b1000 M
b1000 P
1&
1"
#560
0&
0"
#570
b1001 =
b1001 M
b1001 P
1&
1"
#580
0&
0"
#590
b1010 =
b1010 M
b1010 P
1&
1"
#600
0&
0"
#610
b1011 =
b1011 M
b1011 P
1&
1"
#620
0&
0"
#630
b1100 =
b1100 M
b1100 P
1&
1"
#640
0&
0"
#650
b1101 =
b1101 M
b1101 P
1&
1"
#660
0&
0"
#670
b1110 =
b1110 M
b1110 P
1&
1"
#680
0&
0"
#690
b1111 =
b1111 M
b1111 P
1&
1"
#700
0&
0"
#710
b10000 =
b10000 M
b10000 P
1&
1"
#720
0&
0"
#730
b10001 =
b10001 M
b10001 P
1&
1"
#740
0&
0"
#750
b10010 =
b10010 M
b10010 P
1&
1"
#760
0&
0"
#770
b10011 =
b10011 M
b10011 P
1&
1"
#780
0&
0"
#790
b10100 =
b10100 M
b10100 P
1&
1"
#800
0&
0"
#810
b10101 =
b10101 M
b10101 P
1&
1"
#820
0&
0"
#830
b10110 =
b10110 M
b10110 P
1&
1"
#840
0&
0"
#850
b10111 =
b10111 M
b10111 P
1&
1"
#860
0&
0"
#870
b11000 =
b11000 M
b11000 P
1&
1"
#880
0&
0"
#890
b11001 =
b11001 M
b11001 P
1&
1"
#900
0&
0"
#910
b11010 =
b11010 M
b11010 P
1&
1"
#920
0&
0"
#930
b11011 =
b11011 M
b11011 P
1&
1"
#940
0&
0"
#950
b11100 =
b11100 M
b11100 P
1&
1"
#960
0&
0"
#970
b11101 =
b11101 M
b11101 P
1&
1"
#980
0&
0"
#990
b11110 =
b11110 M
b11110 P
1&
1"
#1000
0&
0"
#1010
b11111 =
b11111 M
b11111 P
1&
1"
#1020
0&
0"
#1030
b100000 =
b100000 M
b100000 P
1&
1"
#1040
0&
0"
#1050
b100001 =
b100001 M
b100001 P
1&
1"
#1060
0&
0"
#1070
b100010 =
b100010 M
b100010 P
1&
1"
#1080
0&
0"
#1090
b100011 =
b100011 M
b100011 P
1&
1"
#1100
0&
0"
#1110
b100100 =
b100100 M
b100100 P
1&
1"
#1120
0&
0"
#1130
b100101 =
b100101 M
b100101 P
1&
1"
#1140
0&
0"
#1150
b100110 =
b100110 M
b100110 P
1&
1"
#1160
0&
0"
#1170
b100111 =
b100111 M
b100111 P
1&
1"
#1180
0&
0"
#1190
b101000 =
b101000 M
b101000 P
1&
1"
#1200
0&
0"
#1210
b101001 =
b101001 M
b101001 P
1&
1"
#1220
0&
0"
#1230
b101010 =
b101010 M
b101010 P
1&
1"
#1240
0&
0"
#1250
b101011 =
b101011 M
b101011 P
1&
1"
#1260
0&
0"
#1270
b101100 =
b101100 M
b101100 P
1&
1"
#1280
0&
0"
#1290
b101101 =
b101101 M
b101101 P
1&
1"
#1300
0&
0"
#1310
b101110 =
b101110 M
b101110 P
1&
1"
#1320
0&
0"
#1330
b101111 =
b101111 M
b101111 P
1&
1"
#1340
0&
0"
#1350
b110000 =
b110000 M
b110000 P
1&
1"
#1360
0&
0"
#1370
b110001 =
b110001 M
b110001 P
1&
1"
#1380
0&
0"
#1390
b110010 =
b110010 M
b110010 P
1&
1"
#1400
0&
0"
#1410
b110011 =
b110011 M
b110011 P
1&
1"
#1420
0&
0"
#1430
b110100 =
b110100 M
b110100 P
1&
1"
#1440
0&
0"
#1450
b110101 =
b110101 M
b110101 P
1&
1"
#1460
0&
0"
#1470
b110110 =
b110110 M
b110110 P
1&
1"
#1480
0&
0"
#1490
b110111 =
b110111 M
b110111 P
1&
1"
#1500
0&
0"
#1510
b111000 =
b111000 M
b111000 P
1&
1"
#1520
0&
0"
#1530
b111001 =
b111001 M
b111001 P
1&
1"
#1540
0&
0"
#1550
b111010 =
b111010 M
b111010 P
1&
1"
#1560
0&
0"
#1570
b111011 =
b111011 M
b111011 P
1&
1"
#1580
0&
0"
#1590
b111100 =
b111100 M
b111100 P
1&
1"
#1600
0&
0"
#1610
b111101 =
b111101 M
b111101 P
1&
1"
#1620
0&
0"
#1630
b111110 =
b111110 M
b111110 P
1&
1"
#1640
0&
0"
#1650
b111111 =
b111111 M
b111111 P
1&
1"
#1660
0&
0"
#1670
b1000000 =
b1000000 M
b1000000 P
1&
1"
#1680
0&
0"
#1690
b1000001 =
b1000001 M
b1000001 P
1&
1"
#1700
0&
0"
#1710
b1000010 =
b1000010 M
b1000010 P
1&
1"
#1720
0&
0"
#1730
b1000011 =
b1000011 M
b1000011 P
1&
1"
#1740
0&
0"
#1750
b1000100 =
b1000100 M
b1000100 P
1&
1"
#1760
0&
0"
#1770
b1000101 =
b1000101 M
b1000101 P
1&
1"
#1780
0&
0"
#1790
b1000110 =
b1000110 M
b1000110 P
1&
1"
#1800
0&
0"
#1810
b1000111 =
b1000111 M
b1000111 P
1&
1"
#1820
0&
0"
#1830
b1001000 =
b1001000 M
b1001000 P
1&
1"
#1840
0&
0"
#1850
b1001001 =
b1001001 M
b1001001 P
1&
1"
#1860
0&
0"
#1870
b1001010 =
b1001010 M
b1001010 P
1&
1"
#1880
0&
0"
#1890
b1001011 =
b1001011 M
b1001011 P
1&
1"
#1900
0&
0"
#1910
b1001100 =
b1001100 M
b1001100 P
1&
1"
#1920
0&
0"
#1930
b1001101 =
b1001101 M
b1001101 P
1&
1"
#1940
0&
0"
#1950
b1001110 =
b1001110 M
b1001110 P
1&
1"
#1960
0&
0"
#1970
b1001111 =
b1001111 M
b1001111 P
1&
1"
#1980
0&
0"
#1990
b1010000 =
b1010000 M
b1010000 P
1&
1"
#2000
0&
0"
#2010
b1010001 =
b1010001 M
b1010001 P
1&
1"
#2020
0&
0"
#2030
b1010010 =
b1010010 M
b1010010 P
1&
1"
#2040
0&
0"
#2050
b1010011 =
b1010011 M
b1010011 P
1&
1"
#2060
0&
0"
#2070
b1010100 =
b1010100 M
b1010100 P
1&
1"
#2080
0&
0"
#2090
b1010101 =
b1010101 M
b1010101 P
1&
1"
#2100
0&
0"
#2110
b1010110 =
b1010110 M
b1010110 P
1&
1"
#2120
0&
0"
#2130
b1010111 =
b1010111 M
b1010111 P
1&
1"
#2140
0&
0"
#2150
b1011000 =
b1011000 M
b1011000 P
1&
1"
#2160
0&
0"
#2170
b1011001 =
b1011001 M
b1011001 P
1&
1"
#2180
0&
0"
#2190
b1011010 =
b1011010 M
b1011010 P
1&
1"
#2200
0&
0"
#2210
b1011011 =
b1011011 M
b1011011 P
1&
1"
#2220
0&
0"
#2230
b1011100 =
b1011100 M
b1011100 P
1&
1"
#2240
0&
0"
#2250
b1011101 =
b1011101 M
b1011101 P
1&
1"
#2260
0&
0"
#2270
b1011110 =
b1011110 M
b1011110 P
1&
1"
#2280
0&
0"
#2290
b1011111 =
b1011111 M
b1011111 P
1&
1"
#2300
0&
0"
#2310
b1100000 =
b1100000 M
b1100000 P
1&
1"
#2320
0&
0"
#2330
b1100001 =
b1100001 M
b1100001 P
1&
1"
#2340
0&
0"
#2350
b1100010 =
b1100010 M
b1100010 P
1&
1"
#2360
0&
0"
#2370
b1100011 =
b1100011 M
b1100011 P
1&
1"
#2380
0&
0"
#2390
b1100100 =
b1100100 M
b1100100 P
1&
1"
#2400
0&
0"
#2410
b1100101 =
b1100101 M
b1100101 P
1&
1"
#2420
0&
0"
